{
  "ts": "2025-12-23T14:21:32.659826Z",
  "symbol": "KGEN",
  "token": "0xF3d5b4c34Ed623478cc5141861776E6cf7AE3A1E",
  "price_usd": 0.2328,
  "main_pair_hint": "0x81965714e2A1EC25fB8BcB3DE60a11FE6bCA929a",
  "window_minutes": 40,
  "stats": {
    "total_swaps_scanned": 197,
    "total_swaps_in_window": 197,
    "buys_ge_min_usd": 36,
    "wallet_unici_ge_min_usd": 34,
    "wallet_valutati_topk": 20,
    "wallet_tenuti": 0,
    "wallet_scartati_old": 20,
    "dexscreener_activity_bucket": "h1",
    "dexscreener_bucket_buys": 66,
    "dexscreener_bucket_sells": 89
  },
  "agg": {
    "buyers_total_usd_window_all": 4745.333326458153,
    "buyers_unique_all": 34,
    "top_spenders_all": [
      {
        "address": "0xc230adfedf82ffd17069b610b6dbe1f74c5020ca",
        "sum_buys_usd_window": 286.43471203534426
      },
      {
        "address": "0x89266caac5ed4a1d106a05bea1a5ea8333052661",
        "sum_buys_usd_window": 239.08268027963612
      },
      {
        "address": "0x158732f91e1dd57f54acd87811c4e50856327dea",
        "sum_buys_usd_window": 227.70000000000005
      },
      {
        "address": "0x840c3ef842c7ed74f71dd767ccda4907609f7dca",
        "sum_buys_usd_window": 218.45724731841864
      },
      {
        "address": "0xa209fab2252cc7d4b7d841fe4db7b69411399501",
        "sum_buys_usd_window": 207.41269699787384
      },
      {
        "address": "0x5b7e60e7562835ab9725113ee3803e35846c21f9",
        "sum_buys_usd_window": 200.0
      },
      {
        "address": "0xd6ff0c7138e10cf7784c3c8c8d7d3bafc90ea74c",
        "sum_buys_usd_window": 194.58301349627354
      },
      {
        "address": "0x18b8a435072a964983e3fff19301d2a83e4aee57",
        "sum_buys_usd_window": 151.8
      },
      {
        "address": "0x95787c6d7b5258ef3be0b72d8c39b07227caa266",
        "sum_buys_usd_window": 151.8
      },
      {
        "address": "0xcfc3faa0d398f77038c1bef9a69764d1fe2ccfde",
        "sum_buys_usd_window": 151.8
      },
      {
        "address": "0x80c5a556d90a6207dc73e422ef5d435c81831a8b",
        "sum_buys_usd_window": 151.8
      },
      {
        "address": "0xc16b14a4df90c04c7d28a96fd01efd6df3fc9b95",
        "sum_buys_usd_window": 150.10793558411464
      },
      {
        "address": "0xa1d573b93a4c6521353fa24b7dc664a01f2c30d6",
        "sum_buys_usd_window": 148.22677059593266
      },
      {
        "address": "0xd7fb558c007a6171f1be8c84e892dc48754669e4",
        "sum_buys_usd_window": 142.03880363753333
      },
      {
        "address": "0x4e2654d3003e0022f6b0355d0e0f11e37770f3a9",
        "sum_buys_usd_window": 130.34683739103087
      },
      {
        "address": "0xcf466b58a439c4c52ada79a09e0876efc3c2269b",
        "sum_buys_usd_window": 127.91633725101808
      },
      {
        "address": "0x1ea99b62efc93982b58e48d5bcd6ff931180fb5a",
        "sum_buys_usd_window": 117.47696762194656
      },
      {
        "address": "0xe98cdf40a8241b93f0be4c087420498cc42e3171",
        "sum_buys_usd_window": 115.29644405359116
      },
      {
        "address": "0xe691e84cfdf320effd4299f66f7a79f33298a820",
        "sum_buys_usd_window": 115.16625382926667
      },
      {
        "address": "0xbb32a653ac207e886d2a121aeec464b563d9b166",
        "sum_buys_usd_window": 109.08651123156346
      }
    ]
  }
}