{
  "ts": "2025-12-01T07:29:32.468510Z",
  "symbol": "B2",
  "token": "0x783c3f003f172c6Ac5AC700218a357d2D66Ee2a2",
  "price_usd": 0.511,
  "main_pair_hint": "0xc1A780989734a0e5df875cEbe410748562e1c5e6",
  "window_minutes": 40,
  "stats": {
    "total_swaps_scanned": 319,
    "total_swaps_in_window": 319,
    "buys_ge_min_usd": 190,
    "wallet_unici_ge_min_usd": 78,
    "wallet_valutati_topk": 20,
    "wallet_tenuti": 0,
    "wallet_scartati_old": 20,
    "dexscreener_activity_bucket": "h1",
    "dexscreener_bucket_buys": 417,
    "dexscreener_bucket_sells": 377
  },
  "agg": {
    "buyers_total_usd_window_all": 43626.85903887682,
    "buyers_unique_all": 78,
    "top_spenders_all": [
      {
        "address": "0x12c43f031b112fc9a31d4457e3cdaaa67a43441f",
        "sum_buys_usd_window": 7556.876437846237
      },
      {
        "address": "0xe4716f4e6f5651b73b94494e8a9488e8c02e7247",
        "sum_buys_usd_window": 2436.5828764023613
      },
      {
        "address": "0x230403372a79703986f3e20822215547fb34b60a",
        "sum_buys_usd_window": 1980.632601596368
      },
      {
        "address": "0xb578314a1cd4e81284405638a6bed9597b43f9e1",
        "sum_buys_usd_window": 1776.1718832959987
      },
      {
        "address": "0xb80b21025f8e166783c1e2aec8a1d3df62370b4f",
        "sum_buys_usd_window": 1349.7830420698533
      },
      {
        "address": "0x43b8ed1e6649f71304d58487c88f0c3cedd57cf5",
        "sum_buys_usd_window": 1306.6659846682253
      },
      {
        "address": "0x7eb755ce59653f7023e324310818168961839d12",
        "sum_buys_usd_window": 1233.3610057823555
      },
      {
        "address": "0x7eb821c02525d899f82c31b9760d105396694c9b",
        "sum_buys_usd_window": 1159.8875099679362
      },
      {
        "address": "0x1e33a43dd30c709bf120c8669a2249e4791ea3b2",
        "sum_buys_usd_window": 1112.244944939113
      },
      {
        "address": "0xb154d918199179182ec177cf268ecb535904c983",
        "sum_buys_usd_window": 960.7305728401919
      },
      {
        "address": "0x6f120109c1096a6ae9bb123e39f9d907da8acf7d",
        "sum_buys_usd_window": 940.7937070629738
      },
      {
        "address": "0x2a201998350dc41f5c71d83d6e8decbd0badf801",
        "sum_buys_usd_window": 940.0325824875075
      },
      {
        "address": "0x709c61d0009eab2d6264d2efb6d6d3d592f7cafb",
        "sum_buys_usd_window": 917.2703588373826
      },
      {
        "address": "0xbd63460e1650c6c8999ab0b028f72a6f7a957a6e",
        "sum_buys_usd_window": 872.1854152159858
      },
      {
        "address": "0x18f063eac520ca6760bfca45e528dbf658e15a4b",
        "sum_buys_usd_window": 865.9227302631332
      },
      {
        "address": "0xafe9a934a5bbf601412653706992dd910200ac82",
        "sum_buys_usd_window": 851.040844055826
      },
      {
        "address": "0x1b8f9a533dff227e8ae1c9ddaa0e80644272a8c4",
        "sum_buys_usd_window": 822.7790268327096
      },
      {
        "address": "0x51ec7b4269741b9e67f34858bdb6508e4db77303",
        "sum_buys_usd_window": 662.8504185014342
      },
      {
        "address": "0xd7c0e1b504563ce64f7e5252e2077440106af713",
        "sum_buys_usd_window": 637.3104644508823
      },
      {
        "address": "0x89b0e1d925619775b8cf18e78acb3e2418585251",
        "sum_buys_usd_window": 629.883419352798
      }
    ]
  }
}