{"id": "mina-protocol", "symbol": "mina", "name": "Mina Protocol", "web_slug": "mina-protocol", "asset_platform_id": null, "platforms": {"": ""}, "detail_platforms": {"": {"decimal_place": null, "contract_address": ""}}, "block_time_in_minutes": 0, "hashing_algorithm": null, "categories": ["Smart Contract Platform", "Layer 1 (L1)", "Zero Knowledge (ZK)", "FTX Holdings", "Paradigm Portfolio", "Coinbase Ventures Portfolio", "Multicoin Capital Portfolio", "Proof of Stake (PoS)", "Pantera Capital Portfolio", "Circle Ventures Portfolio", "Privacy Blockchain", "Polychain Capital Portfolio", "Made in USA", "Coinbase 50 Index"], "preview_listing": false, "public_notice": null, "additional_notices": [], "description": {"en": "The world's lightest blockchain, powered by participants. Mina is building a privacy-preserving gateway between the real world and crypto \u2014 and the infrastructure for the secure, democratic future we all deserve."}, "links": {"homepage": ["https://minaprotocol.com/"], "whitepaper": "", "blockchain_site": ["https://minaexplorer.com/", "https://hubble.figment.io/mina/chains/mainnet", "https://minascan.io/", "https://minataur.net/"], "official_forum_url": [], "chat_url": ["https://discord.com/invite/Vexf4ED"], "announcement_url": ["https://medium.com/@minaprotocol"], "snapshot_url": null, "twitter_screen_name": "minaprotocol", "facebook_username": "", "bitcointalk_thread_identifier": null, "telegram_channel_identifier": "minaprotocol", "subreddit_url": "https://www.reddit.com/r/MinaProtocol/", "repos_url": {"github": ["https://github.com/MinaProtocol/mina"], "bitbucket": []}}, "image": {"thumb": "https://coin-images.coingecko.com/coins/images/15628/thumb/JM4_vQ34_400x400.png?1696515261", "small": "https://coin-images.coingecko.com/coins/images/15628/small/JM4_vQ34_400x400.png?1696515261", "large": "https://coin-images.coingecko.com/coins/images/15628/large/JM4_vQ34_400x400.png?1696515261"}, "country_origin": "", "genesis_date": null, "sentiment_votes_up_percentage": 82.35, "sentiment_votes_down_percentage": 17.65, "watchlist_portfolio_users": 100049, "market_cap_rank": 275, "status_updates": [], "last_updated": "2025-11-07T14:54:08.811Z", "tickers": [{"base": "MINA", "target": "USDT", "market": {"name": "Binance", "identifier": "binance", "has_trading_incentive": false}, "last": 0.1841, "volume": 174041858.6, "converted_last": {"btc": 1.83e-06, "eth": 5.633e-05, "usd": 0.183977}, "converted_volume": {"btc": 318.904, "eth": 9804, "usd": 32019748}, "trust_score": "green", "bid_ask_spread_percentage": 0.108814, "timestamp": "2025-11-07T14:53:31+00:00", "last_traded_at": "2025-11-07T14:53:31+00:00", "last_fetch_at": "2025-11-07T14:53:31+00:00", "is_anomaly": false, "is_stale": false, "trade_url": "https://www.binance.com/en/trade/MINA_USDT?ref=37754157", "token_info_url": null, "coin_id": "mina-protocol", "target_coin_id": "tether", "coin_mcap_usd": 229614008.36336115}, {"base": "MINA", "target": "USDT", "market": {"name": "Bybit", "identifier": "bybit_spot", "has_trading_incentive": false}, "last": 0.1845, "volume": 56838764.46, "converted_last": {"btc": 1.83e-06, "eth": 5.628e-05, "usd": 0.184377}, "converted_volume": {"btc": 95.372, "eth": 2925, "usd": 9584301}, "trust_score": "green", "bid_ask_spread_percentage": 0.053191, "timestamp": "2025-11-07T14:52:38+00:00", "last_traded_at": "2025-11-07T14:52:38+00:00", "last_fetch_at": "2025-11-07T14:54:07+00:00", "is_anomaly": false, "is_stale": false, "trade_url": "https://www.bybit.com/trade/spot/MINA/USDT", "token_info_url": null, "coin_id": "mina-protocol", "target_coin_id": "tether", "coin_mcap_usd": 229614008.36336115}, {"base": "MINA", "target": "USDT", "market": {"name": "MEXC", "identifier": "mxc", "has_trading_incentive": false}, "last": 0.18445, "volume": 99456119.93, "converted_last": {"btc": 1.83e-06, "eth": 5.637e-05, "usd": 0.184327}, "converted_volume": {"btc": 166.856, "eth": 5127, "usd": 16764989}, "trust_score": "green", "bid_ask_spread_percentage": 0.11872, "timestamp": "2025-11-07T14:53:54+00:00", "last_traded_at": "2025-11-07T14:53:54+00:00", "last_fetch_at": "2025-11-07T14:53:54+00:00", "is_anomaly": false, "is_stale": false, "trade_url": "https://www.mexc.com/exchange/MINA_USDT", "token_info_url": null, "coin_id": "mina-protocol", "target_coin_id": "tether", "coin_mcap_usd": 229614008.36336115}, {"base": "MINA", "target": "USDT", "market": {"name": "KuCoin", "identifier": "kucoin", "has_trading_incentive": false}, "last": 0.186, "volume": 0.0, "converted_last": {"btc": 1.85e-06, "eth": 5.685e-05, "usd": 0.185876}, "converted_volume": {"btc": 70.706, "eth": 2173, "usd": 7104239}, "trust_score": "green", "bid_ask_spread_percentage": 0.053591, "timestamp": "2025-11-07T14:53:55+00:00", "last_traded_at": "2025-11-07T14:53:55+00:00", "last_fetch_at": "2025-11-07T14:53:55+00:00", "is_anomaly": false, "is_stale": false, "trade_url": "https://www.kucoin.com/trade/MINA-USDT", "token_info_url": null, "coin_id": "mina-protocol", "target_coin_id": "tether", "coin_mcap_usd": 229614008.36336115}, {"base": "MINA", "target": "USDT", "market": {"name": "Gate", "identifier": "gate", "has_trading_incentive": false}, "last": 0.18483, "volume": 58965667.0, "converted_last": {"btc": 1.84e-06, "eth": 5.638e-05, "usd": 0.184707}, "converted_volume": {"btc": 99.129, "eth": 3041, "usd": 9961915}, "trust_score": "green", "bid_ask_spread_percentage": 0.10297, "timestamp": "2025-11-07T14:54:08+00:00", "last_traded_at": "2025-11-07T14:54:08+00:00", "last_fetch_at": "2025-11-07T14:54:08+00:00", "is_anomaly": false, "is_stale": false, "trade_url": "https://www.gate.com/trade/MINA_USDT", "token_info_url": null, "coin_id": "mina-protocol", "target_coin_id": "tether", "coin_mcap_usd": 229614008.36336115}, {"base": "MINA", "target": "USDT", "market": {"name": "OKX", "identifier": "okex", "has_trading_incentive": false}, "last": 0.184, "volume": 44805332.696154, "converted_last": {"btc": 1.83e-06, "eth": 5.625e-05, "usd": 0.183926}, "converted_volume": {"btc": 82.018, "eth": 2520, "usd": 8240884}, "trust_score": "green", "bid_ask_spread_percentage": 0.108637, "timestamp": "2025-11-07T14:52:03+00:00", "last_traded_at": "2025-11-07T14:52:03+00:00", "last_fetch_at": "2025-11-07T14:53:40+00:00", "is_anomaly": false, "is_stale": false, "trade_url": "https://www.okx.com/trade-spot/mina-usdt", "token_info_url": null, "coin_id": "mina-protocol", "target_coin_id": "tether", "coin_mcap_usd": 229614008.36336115}, {"base": "MINA", "target": "USDT", "market": {"name": "LBank", "identifier": "lbank", "has_trading_incentive": false}, "last": 0.1828, "volume": 35861293.472, "converted_last": {"btc": 1.82e-06, "eth": 5.577e-05, "usd": 0.182681}, "converted_volume": {"btc": 65.171, "eth": 2000, "usd": 6551180}, "trust_score": "green", "bid_ask_spread_percentage": 0.108873, "timestamp": "2025-11-07T14:50:10+00:00", "last_traded_at": "2025-11-07T14:50:10+00:00", "last_fetch_at": "2025-11-07T14:50:10+00:00", "is_anomaly": false, "is_stale": false, "trade_url": "https://www.lbank.com/trade/mina_usdt", "token_info_url": null, "coin_id": "mina-protocol", "target_coin_id": "tether", "coin_mcap_usd": 229614008.36336115}, {"base": "MINA", "target": "KRW", "market": {"name": "Upbit", "identifier": "upbit", "has_trading_incentive": false}, "last": 275.0, "volume": 197594982.81331334, "converted_last": {"btc": 1.88e-06, "eth": 5.768e-05, "usd": 0.188378}, "converted_volume": {"btc": 370.721, "eth": 11397, "usd": 37222532}, "trust_score": "green", "bid_ask_spread_percentage": 0.722022, "timestamp": "2025-11-07T14:53:31+00:00", "last_traded_at": "2025-11-07T14:53:31+00:00", "last_fetch_at": "2025-11-07T14:53:31+00:00", "is_anomaly": false, "is_stale": false, "trade_url": "https://upbit.com/exchange?code=CRIX.UPBIT.KRW-MINA", "token_info_url": null, "coin_id": "mina-protocol", "coin_mcap_usd": 229614008.36336115}, {"base": "MINA", "target": "USDT", "market": {"name": "BYDFi", "identifier": "bydfi", "has_trading_incentive": false}, "last": 0.1824, "volume": 13470217.9, "converted_last": {"btc": 1.81e-06, "eth": 5.575e-05, "usd": 0.182285}, "converted_volume": {"btc": 24.439923, "eth": 750.907, "usd": 2455423}, "trust_score": "green", "bid_ask_spread_percentage": 0.061463, "timestamp": "2025-11-07T14:51:16+00:00", "last_traded_at": "2025-11-07T14:51:16+00:00", "last_fetch_at": "2025-11-07T14:51:16+00:00", "is_anomaly": false, "is_stale": false, "trade_url": "https://www.bydfi.com/en/spot/mina_usdt", "token_info_url": null, "coin_id": "mina-protocol", "target_coin_id": "tether", "coin_mcap_usd": 229614008.36336115}, {"base": "MINA", "target": "USDT", "market": {"name": "CoinW", "identifier": "coinw", "has_trading_incentive": false}, "last": 0.1824, "volume": 58620328.7, "converted_last": {"btc": 1.81e-06, "eth": 5.564e-05, "usd": 0.182255}, "converted_volume": {"btc": 106.283, "eth": 3262, "usd": 10683843}, "trust_score": "green", "bid_ask_spread_percentage": 0.327869, "timestamp": "2025-11-07T14:50:34+00:00", "last_traded_at": "2025-11-07T14:50:34+00:00", "last_fetch_at": "2025-11-07T14:50:34+00:00", "is_anomaly": false, "is_stale": false, "trade_url": "https://www.coinw.com/spot/minausdt", "token_info_url": null, "coin_id": "mina-protocol", "target_coin_id": "tether", "coin_mcap_usd": 229614008.36336115}, {"base": "MINA", "target": "USDT", "market": {"name": "XT.COM", "identifier": "xt", "has_trading_incentive": false}, "last": 0.1805, "volume": 20992123.6, "converted_last": {"btc": 1.79e-06, "eth": 5.535e-05, "usd": 0.180383}, "converted_volume": {"btc": 35.169252, "eth": 1085, "usd": 3535012}, "trust_score": "green", "bid_ask_spread_percentage": 0.111359, "timestamp": "2025-11-07T14:48:09+00:00", "last_traded_at": "2025-11-07T14:48:09+00:00", "last_fetch_at": "2025-11-07T14:48:09+00:00", "is_anomaly": false, "is_stale": false, "trade_url": "https://www.xt.com/en/trade/mina_usdt", "token_info_url": null, "coin_id": "mina-protocol", "target_coin_id": "tether", "coin_mcap_usd": 229614008.36336115}, {"base": "MINA", "target": "TRY", "market": {"name": "Binance", "identifier": "binance", "has_trading_incentive": false}, "last": 7.74, "volume": 42954837.26, "converted_last": {"btc": 1.83e-06, "eth": 5.616e-05, "usd": 0.183398}, "converted_volume": {"btc": 78.46, "eth": 2412, "usd": 7877844}, "trust_score": "green", "bid_ask_spread_percentage": 0.2574, "timestamp": "2025-11-07T14:52:12+00:00", "last_traded_at": "2025-11-07T14:52:12+00:00", "last_fetch_at": "2025-11-07T14:53:07+00:00", "is_anomaly": false, "is_stale": false, "trade_url": "https://www.binance.com/en/trade/MINA_TRY?ref=37754157", "token_info_url": null, "coin_id": "mina-protocol", "coin_mcap_usd": 229614008.36336115}, {"base": "MINA", "target": "USDT", "market": {"name": "HTX", "identifier": "huobi", "has_trading_incentive": false}, "last": 0.1845, "volume": 17513501.99068708, "converted_last": {"btc": 1.84e-06, "eth": 5.645e-05, "usd": 0.184377}, "converted_volume": {"btc": 29.410028, "eth": 904.167, "usd": 2952936}, "trust_score": "green", "bid_ask_spread_percentage": 0.108637, "timestamp": "2025-11-07T14:53:11+00:00", "last_traded_at": "2025-11-07T14:53:11+00:00", "last_fetch_at": "2025-11-07T14:53:11+00:00", "is_anomaly": false, "is_stale": false, "trade_url": "https://www.huobi.com/en-us/exchange/mina_usdt", "token_info_url": null, "coin_id": "mina-protocol", "target_coin_id": "tether", "coin_mcap_usd": 229614008.36336115}, {"base": "MINA", "target": "USDT", "market": {"name": "OrangeX", "identifier": "orangex", "has_trading_incentive": false}, "last": 0.183, "volume": 8350965.7, "converted_last": {"btc": 1.82e-06, "eth": 5.637e-05, "usd": 0.18289}, "converted_volume": {"btc": 14.079005, "eth": 435.087, "usd": 1411551}, "trust_score": "green", "bid_ask_spread_percentage": 0.053735, "timestamp": "2025-11-07T14:45:22+00:00", "last_traded_at": "2025-11-07T14:45:22+00:00", "last_fetch_at": "2025-11-07T14:45:22+00:00", "is_anomaly": false, "is_stale": false, "trade_url": "https://www.orangex.com/spot/MINA-USDT-SPOT", "token_info_url": null, "coin_id": "mina-protocol", "target_coin_id": "tether", "coin_mcap_usd": 229614008.36336115}, {"base": "MINA", "target": "USDT", "market": {"name": "Pionex", "identifier": "pionex", "has_trading_incentive": false}, "last": 0.1804, "volume": 16325063.6, "converted_last": {"btc": 1.8e-06, "eth": 5.537e-05, "usd": 0.180283}, "converted_volume": {"btc": 27.358845, "eth": 843.792, "usd": 2747529}, "trust_score": "green", "bid_ask_spread_percentage": 0.164926, "timestamp": "2025-11-07T14:48:53+00:00", "last_traded_at": "2025-11-07T14:48:53+00:00", "last_fetch_at": "2025-11-07T14:48:53+00:00", "is_anomaly": false, "is_stale": false, "trade_url": "https://www.pionex.com/en/trade/MINA_USDT/Bot", "token_info_url": null, "coin_id": "mina-protocol", "target_coin_id": "tether", "coin_mcap_usd": 229614008.36336115}, {"base": "MINA", "target": "TRY", "market": {"name": "Paribu", "identifier": "paribu", "has_trading_incentive": false}, "last": 7.77, "volume": 24726058.0, "converted_last": {"btc": 1.83e-06, "eth": 5.625e-05, "usd": 0.183929}, "converted_volume": {"btc": 41.485153, "eth": 1275, "usd": 4168261}, "trust_score": "green", "bid_ask_spread_percentage": 0.2574, "timestamp": "2025-11-07T14:53:37+00:00", "last_traded_at": "2025-11-07T14:53:37+00:00", "last_fetch_at": "2025-11-07T14:53:37+00:00", "is_anomaly": false, "is_stale": false, "trade_url": "https://www.paribu.com/markets/mina_tl?view=classic", "token_info_url": null, "coin_id": "mina-protocol", "coin_mcap_usd": 229614008.36336115}, {"base": "MINA", "target": "USD", "market": {"name": "Kraken", "identifier": "kraken", "has_trading_incentive": false}, "last": 0.1832, "volume": 15004972.55862103, "converted_last": {"btc": 1.82e-06, "eth": 5.609e-05, "usd": 0.1832}, "converted_volume": {"btc": 27.378022, "eth": 841.696, "usd": 2748911}, "trust_score": "green", "bid_ask_spread_percentage": 0.217155, "timestamp": "2025-11-07T14:51:30+00:00", "last_traded_at": "2025-11-07T14:51:30+00:00", "last_fetch_at": "2025-11-07T14:53:20+00:00", "is_anomaly": false, "is_stale": false, "trade_url": "https://pro.kraken.com/app/trade/MINA-USD", "token_info_url": null, "coin_id": "mina-protocol", "coin_mcap_usd": 229614008.36336115}, {"base": "MINA", "target": "USDT", "market": {"name": "DigiFinex", "identifier": "digifinex", "has_trading_incentive": false}, "last": 0.1836, "volume": 6715033.933597, "converted_last": {"btc": 1.83e-06, "eth": 5.618e-05, "usd": 0.183478}, "converted_volume": {"btc": 12.270795, "eth": 377.247, "usd": 1232058}, "trust_score": "green", "bid_ask_spread_percentage": 0.108225, "timestamp": "2025-11-07T14:53:12+00:00", "last_traded_at": "2025-11-07T14:53:12+00:00", "last_fetch_at": "2025-11-07T14:53:12+00:00", "is_anomaly": false, "is_stale": false, "trade_url": "https://www.digifinex.com/en-ww/trade/USDT/MINA", "token_info_url": null, "coin_id": "mina-protocol", "target_coin_id": "tether", "coin_mcap_usd": 229614008.36336115}, {"base": "MINA", "target": "USDT", "market": {"name": "Hibt", "identifier": "hibt", "has_trading_incentive": false}, "last": 0.186, "volume": 6751003.114884151, "converted_last": {"btc": 1.85e-06, "eth": 5.7e-05, "usd": 0.185875}, "converted_volume": {"btc": 11.294612, "eth": 348.433, "usd": 1136270}, "trust_score": "green", "bid_ask_spread_percentage": 0.10917, "timestamp": "2025-11-07T14:46:33+00:00", "last_traded_at": "2025-11-07T14:46:33+00:00", "last_fetch_at": "2025-11-07T14:46:33+00:00", "is_anomaly": false, "is_stale": false, "trade_url": "https://hibt.com/trade/MINA-USDT", "token_info_url": null, "coin_id": "mina-protocol", "target_coin_id": "tether", "coin_mcap_usd": 229614008.36336115}, {"base": "MINA", "target": "USDT", "market": {"name": "WEEX", "identifier": "weex", "has_trading_incentive": false}, "last": 0.1829, "volume": 2734277.301542, "converted_last": {"btc": 1.82e-06, "eth": 5.597e-05, "usd": 0.182778}, "converted_volume": {"btc": 4.976063, "eth": 153.026, "usd": 499766}, "trust_score": "green", "bid_ask_spread_percentage": 0.054348, "timestamp": "2025-11-07T14:52:18+00:00", "last_traded_at": "2025-11-07T14:52:18+00:00", "last_fetch_at": "2025-11-07T14:52:18+00:00", "is_anomaly": false, "is_stale": false, "trade_url": "https://www.weex.com/spot/MINA-USDT", "token_info_url": null, "coin_id": "mina-protocol", "target_coin_id": "tether", "coin_mcap_usd": 229614008.36336115}, {"base": "MINA", "target": "USDT", "market": {"name": "Bitget", "identifier": "bitget", "has_trading_incentive": false}, "last": 0.1848, "volume": 8526705.23, "converted_last": {"btc": 1.84e-06, "eth": 5.648e-05, "usd": 0.184677}, "converted_volume": {"btc": 14.402137, "eth": 442.554, "usd": 1447069}, "trust_score": "green", "bid_ask_spread_percentage": 0.161117, "timestamp": "2025-11-07T14:53:59+00:00", "last_traded_at": "2025-11-07T14:53:59+00:00", "last_fetch_at": "2025-11-07T14:53:59+00:00", "is_anomaly": false, "is_stale": false, "trade_url": "https://www.bitget.com/spot/MINAUSDT", "token_info_url": null, "coin_id": "mina-protocol", "target_coin_id": "tether", "coin_mcap_usd": 229614008.36336115}, {"base": "MINA", "target": "KRW", "market": {"name": "Bithumb", "identifier": "bithumb", "has_trading_incentive": false}, "last": 276.0, "volume": 31375202.75276575, "converted_last": {"btc": 1.88e-06, "eth": 5.789e-05, "usd": 0.189063}, "converted_volume": {"btc": 59.079, "eth": 1816, "usd": 5931888}, "trust_score": "green", "bid_ask_spread_percentage": 0.722022, "timestamp": "2025-11-07T14:53:31+00:00", "last_traded_at": "2025-11-07T14:53:31+00:00", "last_fetch_at": "2025-11-07T14:53:31+00:00", "is_anomaly": false, "is_stale": false, "trade_url": "https://www.bithumb.com/trade/order/MINA_KRW", "token_info_url": null, "coin_id": "mina-protocol", "coin_mcap_usd": 229614008.36336115}, {"base": "MINA", "target": "USD", "market": {"name": "Coinbase Exchange", "identifier": "gdax", "has_trading_incentive": false}, "last": 0.181, "volume": 23069827.657, "converted_last": {"btc": 1.8e-06, "eth": 5.544e-05, "usd": 0.181}, "converted_volume": {"btc": 41.508687, "eth": 1279, "usd": 4175639}, "trust_score": "green", "bid_ask_spread_percentage": 0.552486, "timestamp": "2025-11-07T14:47:13+00:00", "last_traded_at": "2025-11-07T14:47:13+00:00", "last_fetch_at": "2025-11-07T14:47:13+00:00", "is_anomaly": false, "is_stale": false, "trade_url": "https://www.coinbase.com/advanced-trade/spot/MINA-USD", "token_info_url": null, "coin_id": "mina-protocol", "coin_mcap_usd": 229614008.36336115}, {"base": "MINA", "target": "USDT", "market": {"name": "CoinEx", "identifier": "coinex", "has_trading_incentive": false}, "last": 0.180854, "volume": 12585213.72873827, "converted_last": {"btc": 1.8e-06, "eth": 5.543e-05, "usd": 0.180736}, "converted_volume": {"btc": 21.027273, "eth": 648.196, "usd": 2113605}, "trust_score": "green", "bid_ask_spread_percentage": 0.702208, "timestamp": "2025-11-07T14:47:39+00:00", "last_traded_at": "2025-11-07T14:47:39+00:00", "last_fetch_at": "2025-11-07T14:47:39+00:00", "is_anomaly": false, "is_stale": false, "trade_url": "https://www.coinex.com/en/exchange/mina-usdt?", "token_info_url": null, "coin_id": "mina-protocol", "target_coin_id": "tether", "coin_mcap_usd": 229614008.36336115}, {"base": "MINA", "target": "USDT", "market": {"name": "WhiteBIT", "identifier": "whitebit", "has_trading_incentive": false}, "last": 0.1841, "volume": 8563112.5, "converted_last": {"btc": 1.84e-06, "eth": 5.671e-05, "usd": 0.183979}, "converted_volume": {"btc": 15.713566, "eth": 485.6, "usd": 1575431}, "trust_score": "green", "bid_ask_spread_percentage": 0.701565, "timestamp": "2025-11-07T14:45:05+00:00", "last_traded_at": "2025-11-07T14:45:05+00:00", "last_fetch_at": "2025-11-07T14:45:05+00:00", "is_anomaly": false, "is_stale": false, "trade_url": "https://whitebit.com/trade/MINA_USDT", "token_info_url": null, "coin_id": "mina-protocol", "target_coin_id": "tether", "coin_mcap_usd": 229614008.36336115}, {"base": "MINA", "target": "EUR", "market": {"name": "Kraken", "identifier": "kraken", "has_trading_incentive": false}, "last": 0.1577, "volume": 2025987.04249931, "converted_last": {"btc": 1.82e-06, "eth": 5.589e-05, "usd": 0.182546}, "converted_volume": {"btc": 3.683412, "eth": 113.241, "usd": 369836}, "trust_score": "green", "bid_ask_spread_percentage": 0.440252, "timestamp": "2025-11-07T14:51:21+00:00", "last_traded_at": "2025-11-07T14:51:21+00:00", "last_fetch_at": "2025-11-07T14:53:20+00:00", "is_anomaly": false, "is_stale": false, "trade_url": "https://pro.kraken.com/app/trade/MINA-EUR", "token_info_url": null, "coin_id": "mina-protocol", "coin_mcap_usd": 229614008.36336115}, {"base": "MINA", "target": "BTC", "market": {"name": "Binance", "identifier": "binance", "has_trading_incentive": false}, "last": 1.83e-06, "volume": 2029220.5, "converted_last": {"btc": 1.83e-06, "eth": 5.608e-05, "usd": 0.183743}, "converted_volume": {"btc": 3.710198, "eth": 113.805, "usd": 372854}, "trust_score": "green", "bid_ask_spread_percentage": 0.543478, "timestamp": "2025-11-07T14:53:31+00:00", "last_traded_at": "2025-11-07T14:53:31+00:00", "last_fetch_at": "2025-11-07T14:54:02+00:00", "is_anomaly": false, "is_stale": false, "trade_url": "https://www.binance.com/en/trade/MINA_BTC?ref=37754157", "token_info_url": null, "coin_id": "mina-protocol", "target_coin_id": "bitcoin", "coin_mcap_usd": 229614008.36336115}, {"base": "MINA", "target": "EUR", "market": {"name": "Bit2Me", "identifier": "bit2me", "has_trading_incentive": false}, "last": 0.1569, "volume": 1985237.4196977238, "converted_last": {"btc": 1.81e-06, "eth": 5.544e-05, "usd": 0.181618}, "converted_volume": {"btc": 3.326209, "eth": 102.072, "usd": 334358}, "trust_score": "green", "bid_ask_spread_percentage": 0.503145, "timestamp": "2025-11-07T14:50:13+00:00", "last_traded_at": "2025-11-07T14:50:13+00:00", "last_fetch_at": "2025-11-07T14:50:13+00:00", "is_anomaly": false, "is_stale": false, "trade_url": "https://pro.bit2me.com/exchange/MINA-EUR", "token_info_url": null, "coin_id": "mina-protocol", "coin_mcap_usd": 229614008.36336115}, {"base": "MINA", "target": "USDT", "market": {"name": "Bitrue", "identifier": "bitrue", "has_trading_incentive": false}, "last": 0.1855, "volume": 4405872.015, "converted_last": {"btc": 1.84e-06, "eth": 5.669e-05, "usd": 0.185376}, "converted_volume": {"btc": 8.128754, "eth": 249.783, "usd": 816744}, "trust_score": "green", "bid_ask_spread_percentage": 1.445396, "timestamp": "2025-11-07T14:53:42+00:00", "last_traded_at": "2025-11-07T14:53:42+00:00", "last_fetch_at": "2025-11-07T14:53:42+00:00", "is_anomaly": false, "is_stale": false, "trade_url": "https://www.bitrue.com/trade/mina_usdt", "token_info_url": null, "coin_id": "mina-protocol", "target_coin_id": "tether", "coin_mcap_usd": 229614008.36336115}, {"base": "MINA", "target": "EUR", "market": {"name": "OKX", "identifier": "okex", "has_trading_incentive": false}, "last": 0.1578, "volume": 335582.9796, "converted_last": {"btc": 1.82e-06, "eth": 5.593e-05, "usd": 0.182556}, "converted_volume": {"btc": 0.60964528, "eth": 18.768446, "usd": 61263}, "trust_score": "green", "bid_ask_spread_percentage": 0.379747, "timestamp": "2025-11-07T14:50:03+00:00", "last_traded_at": "2025-11-07T14:50:03+00:00", "last_fetch_at": "2025-11-07T14:50:03+00:00", "is_anomaly": false, "is_stale": false, "trade_url": "https://www.okx.com/trade-spot/mina-eur", "token_info_url": null, "coin_id": "mina-protocol", "coin_mcap_usd": 229614008.36336115}, {"base": "MINA", "target": "USDC", "market": {"name": "MEXC", "identifier": "mxc", "has_trading_incentive": false}, "last": 0.18346, "volume": 200124.28, "converted_last": {"btc": 1.83e-06, "eth": 5.61e-05, "usd": 0.183423}, "converted_volume": {"btc": 0.33085429, "eth": 10.166614, "usd": 33243}, "trust_score": "green", "bid_ask_spread_percentage": 0.440576, "timestamp": "2025-11-07T14:53:57+00:00", "last_traded_at": "2025-11-07T14:53:57+00:00", "last_fetch_at": "2025-11-07T14:53:57+00:00", "is_anomaly": false, "is_stale": false, "trade_url": "https://www.mexc.com/exchange/MINA_USDC", "token_info_url": null, "coin_id": "mina-protocol", "target_coin_id": "usd-coin", "coin_mcap_usd": 229614008.36336115}, {"base": "MINA", "target": "USDC", "market": {"name": "BYDFi", "identifier": "bydfi", "has_trading_incentive": false}, "last": 0.1837, "volume": 36037.3, "converted_last": {"btc": 1.83e-06, "eth": 5.626e-05, "usd": 0.183663}, "converted_volume": {"btc": 0.06592221, "eth": 2.027405, "usd": 6618.73}, "trust_score": "green", "bid_ask_spread_percentage": 0.247372, "timestamp": "2025-11-07T14:52:58+00:00", "last_traded_at": "2025-11-07T14:52:58+00:00", "last_fetch_at": "2025-11-07T14:52:58+00:00", "is_anomaly": false, "is_stale": false, "trade_url": "https://www.bydfi.com/en/spot/mina_usdc", "token_info_url": null, "coin_id": "mina-protocol", "target_coin_id": "usd-coin", "coin_mcap_usd": 229614008.36336115}, {"base": "MINA", "target": "BTC", "market": {"name": "CoinEx", "identifier": "coinex", "has_trading_incentive": false}, "last": 1.8429e-06, "volume": 61366.90915944, "converted_last": {"btc": 1.85e-06, "eth": 5.69e-05, "usd": 0.185525}, "converted_volume": {"btc": 0.10462368, "eth": 3.225174, "usd": 10516.49}, "trust_score": "green", "bid_ask_spread_percentage": 0.707994, "timestamp": "2025-11-07T14:47:39+00:00", "last_traded_at": "2025-11-07T14:47:39+00:00", "last_fetch_at": "2025-11-07T14:47:39+00:00", "is_anomaly": false, "is_stale": false, "trade_url": "https://www.coinex.com/en/exchange/mina-btc?", "token_info_url": null, "coin_id": "mina-protocol", "target_coin_id": "bitcoin", "coin_mcap_usd": 229614008.36336115}, {"base": "MINA", "target": "USDT", "market": {"name": "Deepcoin", "identifier": "deepcoin", "has_trading_incentive": false}, "last": 0.1799, "volume": 1097521.58485465, "converted_last": {"btc": 1.79e-06, "eth": 5.507e-05, "usd": 0.179783}, "converted_volume": {"btc": 1.606186, "eth": 49.492869, "usd": 161577}, "trust_score": "yellow", "bid_ask_spread_percentage": 0.055648, "timestamp": "2025-11-07T14:47:15+00:00", "last_traded_at": "2025-11-07T14:47:15+00:00", "last_fetch_at": "2025-11-07T14:47:15+00:00", "is_anomaly": false, "is_stale": false, "trade_url": "https://www.deepcoin.com/en/Spot?currentId=MINA", "token_info_url": null, "coin_id": "mina-protocol", "target_coin_id": "tether", "coin_mcap_usd": 229614008.36336115}, {"base": "MINA", "target": "USDT", "market": {"name": "TokoCrypto", "identifier": "toko_crypto", "has_trading_incentive": false}, "last": 0.1808, "volume": 216888.99734513275, "converted_last": {"btc": 1.8e-06, "eth": 5.549e-05, "usd": 0.180682}, "converted_volume": {"btc": 0.39021929, "eth": 12.035005, "usd": 39188}, "trust_score": "yellow", "bid_ask_spread_percentage": 0.056593, "timestamp": "2025-11-07T14:48:39+00:00", "last_traded_at": "2025-11-07T14:48:39+00:00", "last_fetch_at": "2025-11-07T14:48:39+00:00", "is_anomaly": false, "is_stale": false, "trade_url": "https://www.tokocrypto.com/trade/MINAUSDT", "token_info_url": null, "coin_id": "mina-protocol", "target_coin_id": "tether", "coin_mcap_usd": 229614008.36336115}, {"base": "MINA", "target": "USDT", "market": {"name": "Nami Exchange", "identifier": "nami_exchange", "has_trading_incentive": false}, "last": 0.1826, "volume": 86468.98390000008, "converted_last": {"btc": 1.82e-06, "eth": 5.575e-05, "usd": 0.182485}, "converted_volume": {"btc": 0.15699325, "eth": 4.820645, "usd": 15779.31}, "trust_score": "yellow", "bid_ask_spread_percentage": 0.053967, "timestamp": "2025-11-07T14:50:58+00:00", "last_traded_at": "2025-11-07T14:50:58+00:00", "last_fetch_at": "2025-11-07T14:50:58+00:00", "is_anomaly": false, "is_stale": false, "trade_url": "https://nami.exchange/trade/MINA-USDT", "token_info_url": null, "coin_id": "mina-protocol", "target_coin_id": "tether", "coin_mcap_usd": 229614008.36336115}, {"base": "MINA", "target": "USDT", "market": {"name": "CoinUp.io", "identifier": "coinup", "has_trading_incentive": false}, "last": 0.1856, "volume": 76872.65, "converted_last": {"btc": 1.84e-06, "eth": 5.688e-05, "usd": 0.185476}, "converted_volume": {"btc": 0.12754549, "eth": 3.934718, "usd": 12831.44}, "trust_score": "yellow", "bid_ask_spread_percentage": 0.161117, "timestamp": "2025-11-07T14:46:26+00:00", "last_traded_at": "2025-11-07T14:46:26+00:00", "last_fetch_at": "2025-11-07T14:46:26+00:00", "is_anomaly": false, "is_stale": false, "trade_url": "https://www.coinup.io/en_US/trade/MINA_USDT", "token_info_url": null, "coin_id": "mina-protocol", "target_coin_id": "tether", "coin_mcap_usd": 229614008.36336115}, {"base": "MINA", "target": "USDC", "market": {"name": "Bitget", "identifier": "bitget", "has_trading_incentive": false}, "last": 0.184, "volume": 323927.76, "converted_last": {"btc": 1.83e-06, "eth": 5.615e-05, "usd": 0.183963}, "converted_volume": {"btc": 0.54332806, "eth": 16.665833, "usd": 54601}, "trust_score": "yellow", "bid_ask_spread_percentage": 0.323102, "timestamp": "2025-11-07T14:54:02+00:00", "last_traded_at": "2025-11-07T14:54:02+00:00", "last_fetch_at": "2025-11-07T14:54:02+00:00", "is_anomaly": false, "is_stale": false, "trade_url": "https://www.bitget.com/spot/MINAUSDC", "token_info_url": null, "coin_id": "mina-protocol", "target_coin_id": "usd-coin", "coin_mcap_usd": 229614008.36336115}, {"base": "MINA", "target": "USD", "market": {"name": "CEX.IO", "identifier": "cex", "has_trading_incentive": false}, "last": 0.181, "volume": 146121.324746, "converted_last": {"btc": 1.8e-06, "eth": 5.544e-05, "usd": 0.181}, "converted_volume": {"btc": 0.24893798, "eth": 7.670752, "usd": 25042}, "trust_score": "yellow", "bid_ask_spread_percentage": 0.552486, "timestamp": "2025-11-07T14:47:09+00:00", "last_traded_at": "2025-11-07T14:47:09+00:00", "last_fetch_at": "2025-11-07T14:47:09+00:00", "is_anomaly": false, "is_stale": false, "trade_url": "https://trade.cex.io/spot/MINA-USD", "token_info_url": null, "coin_id": "mina-protocol", "coin_mcap_usd": 229614008.36336115}, {"base": "MINA", "target": "EUR", "market": {"name": "Coinbase Exchange", "identifier": "gdax", "has_trading_incentive": false}, "last": 0.151, "volume": 310240.083, "converted_last": {"btc": 1.74e-06, "eth": 5.362e-05, "usd": 0.174741}, "converted_volume": {"btc": 0.53934292, "eth": 16.635276, "usd": 54212}, "trust_score": "yellow", "bid_ask_spread_percentage": 0.641026, "timestamp": "2025-11-07T13:40:15+00:00", "last_traded_at": "2025-11-07T13:40:15+00:00", "last_fetch_at": "2025-11-07T14:48:20+00:00", "is_anomaly": false, "is_stale": false, "trade_url": "https://www.coinbase.com/advanced-trade/spot/MINA-EUR", "token_info_url": null, "coin_id": "mina-protocol", "coin_mcap_usd": 229614008.36336115}, {"base": "MINA", "target": "USDT", "market": {"name": "CEX.IO", "identifier": "cex", "has_trading_incentive": false}, "last": 0.181, "volume": 229418.28585, "converted_last": {"btc": 1.8e-06, "eth": 5.546e-05, "usd": 0.181072}, "converted_volume": {"btc": 0.39324376, "eth": 12.117377, "usd": 39559}, "trust_score": "yellow", "bid_ask_spread_percentage": 0.552486, "timestamp": "2025-11-07T14:47:09+00:00", "last_traded_at": "2025-11-07T14:47:09+00:00", "last_fetch_at": "2025-11-07T14:47:09+00:00", "is_anomaly": false, "is_stale": false, "trade_url": "https://trade.cex.io/spot/MINA-USDT", "token_info_url": null, "coin_id": "mina-protocol", "target_coin_id": "tether", "coin_mcap_usd": 229614008.36336115}, {"base": "MINA", "target": "USDT", "market": {"name": "CoinCatch", "identifier": "coincatch", "has_trading_incentive": false}, "last": 0.1807, "volume": 198083.82, "converted_last": {"btc": 1.8e-06, "eth": 5.541e-05, "usd": 0.180582}, "converted_volume": {"btc": 0.32883718, "eth": 10.142521, "usd": 33053}, "trust_score": "yellow", "bid_ask_spread_percentage": 0.552792, "timestamp": "2025-11-07T14:48:22+00:00", "last_traded_at": "2025-11-07T14:48:22+00:00", "last_fetch_at": "2025-11-07T14:48:22+00:00", "is_anomaly": false, "is_stale": false, "trade_url": "https://www.coincatch.com/en/spot/MINAUSDT_SPBL", "token_info_url": null, "coin_id": "mina-protocol", "target_coin_id": "tether", "coin_mcap_usd": 229614008.36336115}, {"base": "MINA", "target": "USD", "market": {"name": "Crypto.com Exchange", "identifier": "crypto_com", "has_trading_incentive": false}, "last": 0.18403, "volume": 326263.3, "converted_last": {"btc": 1.83e-06, "eth": 5.637e-05, "usd": 0.18403}, "converted_volume": {"btc": 0.59801779, "eth": 18.391741, "usd": 60042}, "trust_score": "yellow", "bid_ask_spread_percentage": 1.085658, "timestamp": "2025-11-07T14:46:27+00:00", "last_traded_at": "2025-11-07T14:46:27+00:00", "last_fetch_at": "2025-11-07T14:52:39+00:00", "is_anomaly": false, "is_stale": false, "trade_url": "https://crypto.com/exchange/trade/spot/MINA_USD", "token_info_url": null, "coin_id": "mina-protocol", "coin_mcap_usd": 229614008.36336115}, {"base": "MINA", "target": "EUR", "market": {"name": "WhiteBIT", "identifier": "whitebit", "has_trading_incentive": false}, "last": 0.1556, "volume": 320358.3, "converted_last": {"btc": 1.79e-06, "eth": 5.543e-05, "usd": 0.179831}, "converted_volume": {"btc": 0.57461226, "eth": 17.757386, "usd": 57610}, "trust_score": "yellow", "bid_ask_spread_percentage": 1.246106, "timestamp": "2025-11-07T14:45:05+00:00", "last_traded_at": "2025-11-07T14:45:05+00:00", "last_fetch_at": "2025-11-07T14:45:05+00:00", "is_anomaly": false, "is_stale": false, "trade_url": "https://whitebit.com/trade/MINA_EUR", "token_info_url": null, "coin_id": "mina-protocol", "coin_mcap_usd": 229614008.36336115}, {"base": "MINA", "target": "USD", "market": {"name": "OKX", "identifier": "okex", "has_trading_incentive": false}, "last": 0.1823, "volume": 54163.554331, "converted_last": {"btc": 1.81e-06, "eth": 5.575e-05, "usd": 0.1823}, "converted_volume": {"btc": 0.09827241, "eth": 3.019751, "usd": 9874.02}, "trust_score": "yellow", "bid_ask_spread_percentage": 0.485961, "timestamp": "2025-11-07T14:43:39+00:00", "last_traded_at": "2025-11-07T14:43:39+00:00", "last_fetch_at": "2025-11-07T14:53:45+00:00", "is_anomaly": false, "is_stale": false, "trade_url": "https://www.okx.com/trade-spot/mina-usd", "token_info_url": null, "coin_id": "mina-protocol", "coin_mcap_usd": 229614008.36336115}, {"base": "MINA", "target": "KRW", "market": {"name": "Coinone", "identifier": "coinone", "has_trading_incentive": false}, "last": 273.9, "volume": 345063.12398945, "converted_last": {"btc": 1.87e-06, "eth": 5.722e-05, "usd": 0.187459}, "converted_volume": {"btc": 0.64366943, "eth": 19.743665, "usd": 64685}, "trust_score": "yellow", "bid_ask_spread_percentage": 5.263158, "timestamp": "2025-11-07T14:52:58+00:00", "last_traded_at": "2025-11-07T14:52:58+00:00", "last_fetch_at": "2025-11-07T14:54:04+00:00", "is_anomaly": false, "is_stale": false, "trade_url": "https://coinone.co.kr/exchange/trade/mina/krw", "token_info_url": null, "coin_id": "mina-protocol", "coin_mcap_usd": 229614008.36336115}, {"base": "MINA", "target": "TRY", "market": {"name": "Bitlo", "identifier": "bitlo", "has_trading_incentive": false}, "last": 7.71, "volume": 62860.69976972, "converted_last": {"btc": 1.82e-06, "eth": 5.594e-05, "usd": 0.182697}, "converted_volume": {"btc": 0.10278022, "eth": 3.160733, "usd": 10322.63}, "trust_score": "yellow", "bid_ask_spread_percentage": 1.029601, "timestamp": "2025-11-07T14:52:02+00:00", "last_traded_at": "2025-11-07T14:52:02+00:00", "last_fetch_at": "2025-11-07T14:52:02+00:00", "is_anomaly": false, "is_stale": false, "trade_url": "https://www.bitlo.com/kolay-alis-satis/MINA-TRY", "token_info_url": null, "coin_id": "mina-protocol", "coin_mcap_usd": 229614008.36336115}, {"base": "MINA", "target": "GBP", "market": {"name": "Kraken", "identifier": "kraken", "has_trading_incentive": false}, "last": 0.1401, "volume": 304533.25678799, "converted_last": {"btc": 1.83e-06, "eth": 5.639e-05, "usd": 0.184172}, "converted_volume": {"btc": 0.55859841, "eth": 17.173268, "usd": 56086}, "trust_score": "yellow", "bid_ask_spread_percentage": 5.751015, "timestamp": "2025-11-07T14:51:21+00:00", "last_traded_at": "2025-11-07T14:51:21+00:00", "last_fetch_at": "2025-11-07T14:53:20+00:00", "is_anomaly": false, "is_stale": false, "trade_url": "https://pro.kraken.com/app/trade/MINA-GBP", "token_info_url": null, "coin_id": "mina-protocol", "coin_mcap_usd": 229614008.36336115}, {"base": "MINA", "target": "XBT", "market": {"name": "Kraken", "identifier": "kraken", "has_trading_incentive": false}, "last": 1.819e-06, "volume": 58089.54864708, "converted_last": {"btc": 1.82e-06, "eth": 5.598e-05, "usd": 0.182828}, "converted_volume": {"btc": 0.10577449, "eth": 3.251877, "usd": 10620.37}, "trust_score": "yellow", "bid_ask_spread_percentage": 1.787649, "timestamp": "2025-11-07T14:51:21+00:00", "last_traded_at": "2025-11-07T14:51:21+00:00", "last_fetch_at": "2025-11-07T14:53:20+00:00", "is_anomaly": false, "is_stale": false, "trade_url": "https://pro.kraken.com/app/trade/MINA-XBT", "token_info_url": null, "coin_id": "mina-protocol", "target_coin_id": "bitcoin", "coin_mcap_usd": 229614008.36336115}, {"base": "MINA", "target": "KRW", "market": {"name": "Korbit", "identifier": "korbit", "has_trading_incentive": false}, "last": 273.5, "volume": 64551.78993096, "converted_last": {"btc": 1.87e-06, "eth": 5.737e-05, "usd": 0.18735}, "converted_volume": {"btc": 0.11149023, "eth": 3.427599, "usd": 11194.26}, "trust_score": "yellow", "bid_ask_spread_percentage": 5.210142, "timestamp": "2025-11-07T14:48:24+00:00", "last_traded_at": "2025-11-07T14:48:24+00:00", "last_fetch_at": "2025-11-07T14:53:35+00:00", "is_anomaly": false, "is_stale": false, "trade_url": "https://lightning.korbit.co.kr/trade/?market=mina-krw", "token_info_url": null, "coin_id": "mina-protocol", "coin_mcap_usd": 229614008.36336115}, {"base": "MINA", "target": "BTC", "market": {"name": "TokoCrypto", "identifier": "toko_crypto", "has_trading_incentive": false}, "last": 1.8e-06, "volume": 2827.777777777778, "converted_last": {"btc": 1.82e-06, "eth": 5.62e-05, "usd": 0.18301}, "converted_volume": {"btc": 0.0051532, "eth": 0.15893305, "usd": 517.51}, "trust_score": "yellow", "bid_ask_spread_percentage": 1.162791, "timestamp": "2025-11-07T14:48:43+00:00", "last_traded_at": "2025-11-07T14:48:43+00:00", "last_fetch_at": "2025-11-07T14:48:43+00:00", "is_anomaly": false, "is_stale": false, "trade_url": "https://www.tokocrypto.com/trade/MINABTC", "token_info_url": null, "coin_id": "mina-protocol", "target_coin_id": "bitcoin", "coin_mcap_usd": 229614008.36336115}, {"base": "MINA", "target": "USDT", "market": {"name": "WazirX", "identifier": "wazirx", "has_trading_incentive": false}, "last": 0.177, "volume": 4131.0, "converted_last": {"btc": 1.76e-06, "eth": 5.425e-05, "usd": 0.176885}, "converted_volume": {"btc": 0.00726951, "eth": 0.22409286, "usd": 730.71}, "trust_score": "yellow", "bid_ask_spread_percentage": 1.648352, "timestamp": "2025-11-07T14:38:23+00:00", "last_traded_at": "2025-11-07T14:38:23+00:00", "last_fetch_at": "2025-11-07T14:47:44+00:00", "is_anomaly": false, "is_stale": false, "trade_url": null, "token_info_url": null, "coin_id": "mina-protocol", "target_coin_id": "tether", "coin_mcap_usd": 229614008.36336115}, {"base": "MINA", "target": "EUR", "market": {"name": "CEX.IO", "identifier": "cex", "has_trading_incentive": false}, "last": 0.157, "volume": 439.8, "converted_last": {"btc": 1.81e-06, "eth": 5.566e-05, "usd": 0.181695}, "converted_volume": {"btc": 0.00077596, "eth": 0.02391037, "usd": 78.06}, "trust_score": "yellow", "bid_ask_spread_percentage": 1.273885, "timestamp": "2025-11-07T14:47:09+00:00", "last_traded_at": "2025-11-07T14:47:09+00:00", "last_fetch_at": "2025-11-07T14:47:09+00:00", "is_anomaly": false, "is_stale": false, "trade_url": "https://trade.cex.io/spot/MINA-EUR", "token_info_url": null, "coin_id": "mina-protocol", "coin_mcap_usd": 229614008.36336115}, {"base": "MINA", "target": "USDT", "market": {"name": "BTCC", "identifier": "btcc", "has_trading_incentive": false}, "last": 0.1823, "volume": 5248755.5600000005, "converted_last": {"btc": 1.81e-06, "eth": 5.566e-05, "usd": 0.182185}, "converted_volume": {"btc": 8.763469, "eth": 269.092, "usd": 880812}, "trust_score": "red", "bid_ask_spread_percentage": 0.217628, "timestamp": "2025-11-07T14:50:48+00:00", "last_traded_at": "2025-11-07T14:50:48+00:00", "last_fetch_at": "2025-11-07T14:50:48+00:00", "is_anomaly": false, "is_stale": false, "trade_url": "https://www.btcc.com/en-US/spot/MINAUSDT", "token_info_url": null, "coin_id": "mina-protocol", "target_coin_id": "tether", "coin_mcap_usd": 229614008.36336115}, {"base": "MINA", "target": "USDT", "market": {"name": "HitBTC", "identifier": "hitbtc", "has_trading_incentive": false}, "last": 0.1822, "volume": 17009753.704, "converted_last": {"btc": 1.81e-06, "eth": 5.575e-05, "usd": 0.182079}, "converted_volume": {"btc": 28.541476, "eth": 877.717, "usd": 2866535}, "trust_score": "red", "bid_ask_spread_percentage": 1.511063, "timestamp": "2025-11-07T14:50:36+00:00", "last_traded_at": "2025-11-07T14:50:36+00:00", "last_fetch_at": "2025-11-07T14:52:28+00:00", "is_anomaly": false, "is_stale": false, "trade_url": "https://hitbtc.com/MINA-to-USDT", "token_info_url": null, "coin_id": "mina-protocol", "target_coin_id": "tether", "coin_mcap_usd": 229614008.36336115}, {"base": "MINA", "target": "INR", "market": {"name": "CoinDCX", "identifier": "coindcx", "has_trading_incentive": false}, "last": 16.72, "volume": 0.0, "converted_last": {"btc": 1.88e-06, "eth": 5.776e-05, "usd": 0.18853}, "converted_volume": {"btc": 0.33944602, "eth": 10.450133, "usd": 34111}, "trust_score": "red", "bid_ask_spread_percentage": 2.022433, "timestamp": "2025-11-07T14:49:51+00:00", "last_traded_at": "2025-11-07T14:49:51+00:00", "last_fetch_at": "2025-11-07T14:49:51+00:00", "is_anomaly": false, "is_stale": false, "trade_url": "https://coindcx.com/trade/MINAINR", "token_info_url": null, "coin_id": "mina-protocol", "coin_mcap_usd": 229614008.36336115}, {"base": "MINA", "target": "BTC", "market": {"name": "HitBTC", "identifier": "hitbtc", "has_trading_incentive": false}, "last": 1.82e-06, "volume": 0.004, "converted_last": {"btc": 1.82e-06, "eth": 5.605e-05, "usd": 0.183043}, "converted_volume": {"btc": 7.29e-09, "eth": 2.24187e-07, "usd": 0.00073217}, "trust_score": null, "bid_ask_spread_percentage": 2.162162, "timestamp": "2025-11-07T07:03:59+00:00", "last_traded_at": "2025-11-07T07:03:59+00:00", "last_fetch_at": "2025-11-07T14:52:23+00:00", "is_anomaly": false, "is_stale": false, "trade_url": "https://hitbtc.com/MINA-to-BTC", "token_info_url": null, "coin_id": "mina-protocol", "target_coin_id": "bitcoin", "coin_mcap_usd": 229614008.36336115}, {"base": "MINA", "target": "BTC", "market": {"name": "Upbit", "identifier": "upbit", "has_trading_incentive": false}, "last": 1.72e-06, "volume": 2279.71325059, "converted_last": {"btc": 1.73e-06, "eth": 5.318e-05, "usd": 0.173687}, "converted_volume": {"btc": 0.00394356, "eth": 0.12123867, "usd": 395.96}, "trust_score": "yellow", "bid_ask_spread_percentage": 1.630435, "timestamp": "2025-11-07T14:22:33+00:00", "last_traded_at": "2025-11-07T14:22:33+00:00", "last_fetch_at": "2025-11-07T14:53:30+00:00", "is_anomaly": true, "is_stale": false, "trade_url": "https://upbit.com/exchange?code=CRIX.UPBIT.BTC-MINA", "token_info_url": null, "coin_id": "mina-protocol", "target_coin_id": "bitcoin", "coin_mcap_usd": 229614008.36336115}, {"base": "MINA", "target": "USDT", "market": {"name": "Giottus", "identifier": "giottus", "has_trading_incentive": false}, "last": 0.167, "volume": 136.0, "converted_last": {"btc": 1.67e-06, "eth": 5.17e-05, "usd": 0.166912}, "converted_volume": {"btc": 0.00022733, "eth": 0.00703114, "usd": 22.7}, "trust_score": "red", "bid_ask_spread_percentage": 0.01, "timestamp": "2025-11-07T11:29:10+00:00", "last_traded_at": "2025-11-07T11:29:10+00:00", "last_fetch_at": "2025-11-07T11:29:10+00:00", "is_anomaly": true, "is_stale": false, "trade_url": "https://www.giottus.com/tradeview/MINA-USDT", "token_info_url": null, "coin_id": "mina-protocol", "target_coin_id": "tether", "coin_mcap_usd": 229614008.36336115}, {"base": "MINA3L", "target": "USDT", "market": {"name": "Bitrue", "identifier": "bitrue", "has_trading_incentive": false}, "last": 1.78061576, "volume": 44293.948583205, "converted_last": {"btc": 1.771e-05, "eth": 0.0005442, "usd": 1.78}, "converted_volume": {"btc": 0.78444554, "eth": 24.104736, "usd": 78818}, "trust_score": null, "bid_ask_spread_percentage": 2.812189, "timestamp": "2025-11-07T14:53:42+00:00", "last_traded_at": "2025-11-07T14:53:42+00:00", "last_fetch_at": "2025-11-07T14:53:42+00:00", "is_anomaly": true, "is_stale": false, "trade_url": "https://www.bitrue.com/trade/mina3l_usdt", "token_info_url": null, "coin_id": "mina-protocol", "target_coin_id": "tether", "coin_mcap_usd": 229614008.36336115}, {"base": "MINA3S", "target": "USDT", "market": {"name": "Bitrue", "identifier": "bitrue", "has_trading_incentive": false}, "last": 7.94e-06, "volume": 5285470518.6, "converted_last": {"btc": 7.8971e-11, "eth": 2.427e-09, "usd": 7.93e-06}, "converted_volume": {"btc": 0.41739991, "eth": 12.826021, "usd": 41939}, "trust_score": null, "bid_ask_spread_percentage": 3.298153, "timestamp": "2025-11-07T14:53:42+00:00", "last_traded_at": "2025-11-07T14:53:42+00:00", "last_fetch_at": "2025-11-07T14:53:42+00:00", "is_anomaly": true, "is_stale": false, "trade_url": "https://www.bitrue.com/trade/mina3s_usdt", "token_info_url": null, "coin_id": "mina-protocol", "target_coin_id": "tether", "coin_mcap_usd": 229614008.36336115}, {"base": "MINA", "target": "BRL", "market": {"name": "Mercado Bitcoin", "identifier": "mercado_bitcoin", "has_trading_incentive": false}, "last": 0.86060003, "volume": 633.07018458, "converted_last": {"btc": 1.6e-06, "eth": 4.92e-05, "usd": 0.160629}, "converted_volume": {"btc": 0.00101282, "eth": 0.03114878, "usd": 101.69}, "trust_score": null, "bid_ask_spread_percentage": 9.305328, "timestamp": "2025-11-07T14:11:53+00:00", "last_traded_at": "2025-11-07T14:11:53+00:00", "last_fetch_at": "2025-11-07T14:52:51+00:00", "is_anomaly": true, "is_stale": false, "trade_url": null, "token_info_url": null, "coin_id": "mina-protocol", "coin_mcap_usd": 229614008.36336115}, {"base": "MINA", "target": "BTC", "market": {"name": "Upbit Indonesia ", "identifier": "upbit_indonesia", "has_trading_incentive": false}, "last": 1.72e-06, "volume": 2279.71325059, "converted_last": {"btc": 1.71e-06, "eth": 5.284e-05, "usd": 0.172156}, "converted_volume": {"btc": 0.0039024, "eth": 0.12046628, "usd": 392.47}, "trust_score": null, "bid_ask_spread_percentage": null, "timestamp": "2025-11-07T14:27:28+00:00", "last_traded_at": "2025-11-07T14:27:28+00:00", "last_fetch_at": "2025-11-07T14:45:51+00:00", "is_anomaly": true, "is_stale": false, "trade_url": "https://id.upbit.com/exchange?code=CRIX.UPBIT.BTC-MINA", "token_info_url": null, "coin_id": "mina-protocol", "target_coin_id": "bitcoin", "coin_mcap_usd": 229614008.36336115}, {"base": "MINA", "target": "EUR", "market": {"name": "Bitvavo", "identifier": "bitvavo", "has_trading_incentive": false}, "last": 0.10403, "volume": 1471289.15505668, "converted_last": {"btc": 1.11e-06, "eth": 3.228e-05, "usd": 0.119796}, "converted_volume": {"btc": 1.635098, "eth": 47.489848, "usd": 176254}, "trust_score": "green", "bid_ask_spread_percentage": 1.106727, "timestamp": "2025-11-03T12:02:37+00:00", "last_traded_at": "2025-11-03T12:02:37+00:00", "last_fetch_at": "2025-11-03T12:02:37+00:00", "is_anomaly": true, "is_stale": true, "trade_url": "https://account.bitvavo.com/markets/MINA-EUR", "token_info_url": null, "coin_id": "mina-protocol", "coin_mcap_usd": 229614008.36336115}, {"base": "MINA", "target": "INR", "market": {"name": "Giottus", "identifier": "giottus", "has_trading_incentive": false}, "last": 16.2, "volume": 136.0, "converted_last": {"btc": 1.83e-06, "eth": 5.66e-05, "usd": 0.182723}, "converted_volume": {"btc": 0.00024886, "eth": 0.00769719, "usd": 24.85}, "trust_score": null, "bid_ask_spread_percentage": 7.909605, "timestamp": "2025-11-06T18:36:56+00:00", "last_traded_at": "2025-11-06T18:36:56+00:00", "last_fetch_at": "2025-11-07T11:29:11+00:00", "is_anomaly": true, "is_stale": true, "trade_url": "https://www.giottus.com/tradeview/MINA-INR", "token_info_url": null, "coin_id": "mina-protocol", "coin_mcap_usd": 229614008.36336115}]}