{"id": "subsquid", "symbol": "sqd", "name": "SQD", "web_slug": "sqd-2", "asset_platform_id": "arbitrum-one", "platforms": {"arbitrum-one": "0x1337420ded5adb9980cfc35f8f2b054ea86f8ab1", "binance-smart-chain": "0xe50e3d1a46070444f44df911359033f2937fcc13", "base": "0xd4554bea546efa83c1e6b389ecac40ea999b3e78"}, "detail_platforms": {"arbitrum-one": {"decimal_place": 18, "contract_address": "0x1337420ded5adb9980cfc35f8f2b054ea86f8ab1", "geckoterminal_url": "https://www.geckoterminal.com/arbitrum/tokens/0x1337420ded5adb9980cfc35f8f2b054ea86f8ab1"}, "binance-smart-chain": {"decimal_place": 18, "contract_address": "0xe50e3d1a46070444f44df911359033f2937fcc13", "geckoterminal_url": "https://www.geckoterminal.com/bsc/tokens/0xe50e3d1a46070444f44df911359033f2937fcc13"}, "base": {"decimal_place": 18, "contract_address": "0xd4554bea546efa83c1e6b389ecac40ea999b3e78", "geckoterminal_url": "https://www.geckoterminal.com/base/tokens/0xd4554bea546efa83c1e6b389ecac40ea999b3e78"}}, "block_time_in_minutes": 0, "hashing_algorithm": null, "categories": ["Artificial Intelligence (AI)", "Big Data", "Analytics", "BNB Chain Ecosystem", "Arbitrum Ecosystem", "Base Ecosystem"], "preview_listing": false, "public_notice": "Subsquid (SQD) has rebranded to SQD (SQD). For more information, please view this <a href=\"https://x.com/helloSQD/status/1808118120969916482\"target=\"_blank\">announcement</a> on Twitter/X.", "additional_notices": [], "description": {"en": "Subsquid Network is an innovative decentralized data lake and query engine designed to offer developers performant and permissionless access to data, aiming to build a neutral and open internet rooted in Web3 principles. Secured by ZK proofs, the Subsquid network boasts a modular architecture that enables exceptional scalability and developer convenience optimized for blockchain indexing, dApp development, and analytics.\r\n\r\nSubsquid is a response to unscalable and rigid monolithic indexing frameworks that had previously gained popularity and market traction among Web3 developers. Today, these frameworks are struggling to adapt in a rapidly evolving blockchain environment. Additionally, the network serves as a highly efficient and decentralized alternative to centralized infrastructure firms, including large RPC and API providers."}, "links": {"homepage": ["https://sqd.dev"], "whitepaper": "", "blockchain_site": ["https://arbiscan.io/token/0x1337420dED5ADb9980CFc35f8f2B054ea86f8aB1", "https://basescan.org/token/0xd4554bea546efa83c1e6b389ecac40ea999b3e78", "https://bscscan.com/token/0xe50e3d1a46070444f44df911359033f2937fcc13", "https://binplorer.com/address/0xe50e3d1a46070444f44df911359033f2937fcc13"], "official_forum_url": [], "chat_url": [], "announcement_url": ["https://docs.subsquid.io/", "https://blog.subsquid.io/"], "snapshot_url": null, "twitter_screen_name": "hellosqd", "facebook_username": "", "bitcointalk_thread_identifier": null, "telegram_channel_identifier": "subsquid", "subreddit_url": null, "repos_url": {"github": ["https://github.com/subsquid"], "bitbucket": []}}, "image": {"thumb": "https://coin-images.coingecko.com/coins/images/37869/thumb/New_Logo_SQD_Icon.png?1720048443", "small": "https://coin-images.coingecko.com/coins/images/37869/small/New_Logo_SQD_Icon.png?1720048443", "large": "https://coin-images.coingecko.com/coins/images/37869/large/New_Logo_SQD_Icon.png?1720048443"}, "country_origin": "", "genesis_date": null, "contract_address": "0x1337420ded5adb9980cfc35f8f2b054ea86f8ab1", "sentiment_votes_up_percentage": null, "sentiment_votes_down_percentage": null, "watchlist_portfolio_users": 4311, "market_cap_rank": 602, "status_updates": [], "last_updated": "2025-11-07T15:10:30.562Z", "tickers": [{"base": "SQD", "target": "USDT", "market": {"name": "Gate", "identifier": "gate", "has_trading_incentive": false}, "last": 0.07395, "volume": 59608088.06, "converted_last": {"btc": 7.35447e-07, "eth": 2.261e-05, "usd": 0.073896}, "converted_volume": {"btc": 44.952768, "eth": 1382, "usd": 4516740}, "trust_score": "green", "bid_ask_spread_percentage": 0.107585, "timestamp": "2025-11-07T15:08:58+00:00", "last_traded_at": "2025-11-07T15:08:58+00:00", "last_fetch_at": "2025-11-07T15:08:58+00:00", "is_anomaly": false, "is_stale": false, "trade_url": "https://www.gate.com/trade/SQD_USDT", "token_info_url": null, "coin_id": "subsquid", "target_coin_id": "tether", "coin_mcap_usd": 65028498.56333634}, {"base": "SQD", "target": "USDT", "market": {"name": "Toobit", "identifier": "toobit", "has_trading_incentive": false}, "last": 0.07451, "volume": 5896010.89, "converted_last": {"btc": 7.40048e-07, "eth": 2.269e-05, "usd": 0.07446}, "converted_volume": {"btc": 4.466394, "eth": 136.966, "usd": 449384}, "trust_score": "green", "bid_ask_spread_percentage": 0.013457, "timestamp": "2025-11-07T15:04:57+00:00", "last_traded_at": "2025-11-07T15:04:57+00:00", "last_fetch_at": "2025-11-07T15:04:57+00:00", "is_anomaly": false, "is_stale": false, "trade_url": "https://www.toobit.com/en-US/spot/SQD_USDT", "token_info_url": null, "coin_id": "subsquid", "target_coin_id": "tether", "coin_mcap_usd": 65028498.56333634}, {"base": "SQD", "target": "USDT", "market": {"name": "Bitunix", "identifier": "bitunix", "has_trading_incentive": false}, "last": 0.07393, "volume": 5056186.64, "converted_last": {"btc": 7.35238e-07, "eth": 2.263e-05, "usd": 0.073876}, "converted_volume": {"btc": 3.7175, "eth": 114.417, "usd": 373530}, "trust_score": "green", "bid_ask_spread_percentage": 0.013521, "timestamp": "2025-11-07T15:07:23+00:00", "last_traded_at": "2025-11-07T15:07:23+00:00", "last_fetch_at": "2025-11-07T15:08:18+00:00", "is_anomaly": false, "is_stale": false, "trade_url": "https://www.bitunix.com/spot-trade/SQDUSDT", "token_info_url": null, "coin_id": "subsquid", "target_coin_id": "tether", "coin_mcap_usd": 65028498.56333634}, {"base": "SQD", "target": "USD", "market": {"name": "Coinbase Exchange", "identifier": "gdax", "has_trading_incentive": false}, "last": 0.0744, "volume": 21865692.6, "converted_last": {"btc": 7.39869e-07, "eth": 2.269e-05, "usd": 0.0744}, "converted_volume": {"btc": 16.177752, "eth": 496.124, "usd": 1626808}, "trust_score": "green", "bid_ask_spread_percentage": 0.13459, "timestamp": "2025-11-07T15:04:13+00:00", "last_traded_at": "2025-11-07T15:04:13+00:00", "last_fetch_at": "2025-11-07T15:04:13+00:00", "is_anomaly": false, "is_stale": false, "trade_url": "https://www.coinbase.com/advanced-trade/spot/SQD-USD", "token_info_url": null, "coin_id": "subsquid", "coin_mcap_usd": 65028498.56333634}, {"base": "SQD", "target": "USDT", "market": {"name": "HTX", "identifier": "huobi", "has_trading_incentive": false}, "last": 0.074, "volume": 51548835.0249, "converted_last": {"btc": 7.35934e-07, "eth": 2.265e-05, "usd": 0.073946}, "converted_volume": {"btc": 38.819803, "eth": 1195, "usd": 3900567}, "trust_score": "green", "bid_ask_spread_percentage": 0.404313, "timestamp": "2025-11-07T15:08:13+00:00", "last_traded_at": "2025-11-07T15:08:13+00:00", "last_fetch_at": "2025-11-07T15:08:13+00:00", "is_anomaly": false, "is_stale": false, "trade_url": "https://www.huobi.com/en-us/exchange/sqd_usdt", "token_info_url": null, "coin_id": "subsquid", "target_coin_id": "tether", "coin_mcap_usd": 65028498.56333634}, {"base": "SQD", "target": "USDT", "market": {"name": "Bybit", "identifier": "bybit_spot", "has_trading_incentive": false}, "last": 0.07421, "volume": 11842824.03, "converted_last": {"btc": 7.38032e-07, "eth": 2.269e-05, "usd": 0.074156}, "converted_volume": {"btc": 9.21913, "eth": 283.485, "usd": 926315}, "trust_score": "green", "bid_ask_spread_percentage": 0.18873, "timestamp": "2025-11-07T15:08:47+00:00", "last_traded_at": "2025-11-07T15:08:47+00:00", "last_fetch_at": "2025-11-07T15:08:47+00:00", "is_anomaly": false, "is_stale": false, "trade_url": "https://www.bybit.com/trade/spot/SQD/USDT", "token_info_url": null, "coin_id": "subsquid", "target_coin_id": "tether", "coin_mcap_usd": 65028498.56333634}, {"base": "SQD", "target": "USDT", "market": {"name": "KuCoin", "identifier": "kucoin", "has_trading_incentive": false}, "last": 0.0745, "volume": 0.0, "converted_last": {"btc": 7.40907e-07, "eth": 2.28e-05, "usd": 0.074445}, "converted_volume": {"btc": 4.611571, "eth": 141.935, "usd": 463365}, "trust_score": "green", "bid_ask_spread_percentage": 0.188501, "timestamp": "2025-11-07T15:05:56+00:00", "last_traded_at": "2025-11-07T15:05:56+00:00", "last_fetch_at": "2025-11-07T15:08:25+00:00", "is_anomaly": false, "is_stale": false, "trade_url": "https://www.kucoin.com/trade/SQD-USDT", "token_info_url": null, "coin_id": "subsquid", "target_coin_id": "tether", "coin_mcap_usd": 65028498.56333634}, {"base": "SQD", "target": "USDT", "market": {"name": "BitKan", "identifier": "bitkan", "has_trading_incentive": false}, "last": 0.07473, "volume": 4462035.93, "converted_last": {"btc": 7.41682e-07, "eth": 2.273e-05, "usd": 0.074681}, "converted_volume": {"btc": 3.309412, "eth": 101.425, "usd": 333229}, "trust_score": "green", "bid_ask_spread_percentage": 0.134427, "timestamp": "2025-11-07T15:00:28+00:00", "last_traded_at": "2025-11-07T15:00:28+00:00", "last_fetch_at": "2025-11-07T15:00:28+00:00", "is_anomaly": false, "is_stale": false, "trade_url": "https://bitkan.com/trade/SQD-USDT", "token_info_url": null, "coin_id": "subsquid", "target_coin_id": "tether", "coin_mcap_usd": 65028498.56333634}, {"base": "0XE50E3D1A46070444F44DF911359033F2937FCC13", "target": "0X8AC76A51CC950D9822D68B83FE1AD97B32CD580D", "market": {"name": "PancakeSwap V3 (BSC)", "identifier": "pancakeswap-v3-bsc", "has_trading_incentive": false}, "last": 0.07414244172, "volume": 10649558.6657391, "converted_last": {"btc": 7.41593e-07, "eth": 2.281e-05, "usd": 0.074455}, "converted_volume": {"btc": 8.252496, "eth": 253.781, "usd": 828542}, "trust_score": "green", "bid_ask_spread_percentage": 0.603402, "timestamp": "2025-11-07T15:09:10+00:00", "last_traded_at": "2025-11-07T15:09:10+00:00", "last_fetch_at": "2025-11-07T15:09:10+00:00", "is_anomaly": false, "is_stale": false, "trade_url": "https://pancakeswap.finance/swap?inputCurrency=0xe50e3d1a46070444f44df911359033f2937fcc13&outputCurrency=0x8ac76a51cc950d9822d68b83fe1ad97b32cd580d", "token_info_url": null, "coin_id": "subsquid", "target_coin_id": "binance-bridged-usdc-bnb-smart-chain", "coin_mcap_usd": 65028498.56333634}, {"base": "SQD", "target": "THB", "market": {"name": "Bitkub", "identifier": "bitkub", "has_trading_incentive": false}, "last": 2.4, "volume": 6962288.59972885, "converted_last": {"btc": 7.37742e-07, "eth": 2.267e-05, "usd": 0.074207}, "converted_volume": {"btc": 5.136374, "eth": 157.84, "usd": 516650}, "trust_score": "green", "bid_ask_spread_percentage": 0.416667, "timestamp": "2025-11-07T15:07:26+00:00", "last_traded_at": "2025-11-07T15:07:26+00:00", "last_fetch_at": "2025-11-07T15:07:26+00:00", "is_anomaly": false, "is_stale": false, "trade_url": "https://www.bitkub.com/market/SQD", "token_info_url": null, "coin_id": "subsquid", "coin_mcap_usd": 65028498.56333634}, {"base": "SQDBSC", "target": "USDT", "market": {"name": "Hibt", "identifier": "hibt", "has_trading_incentive": false}, "last": 0.0747, "volume": 4503727.497749995, "converted_last": {"btc": 7.42526e-07, "eth": 2.278e-05, "usd": 0.074658}, "converted_volume": {"btc": 3.390244, "eth": 104.011, "usd": 340876}, "trust_score": "green", "bid_ask_spread_percentage": 0.533333, "timestamp": "2025-11-07T15:03:18+00:00", "last_traded_at": "2025-11-07T15:03:18+00:00", "last_fetch_at": "2025-11-07T15:03:18+00:00", "is_anomaly": false, "is_stale": false, "trade_url": "https://hibt.com/trade/SQDBSC-USDT", "token_info_url": null, "coin_id": "subsquid", "target_coin_id": "tether", "coin_mcap_usd": 65028498.56333634}, {"base": "SQD", "target": "USDT", "market": {"name": "WEEX", "identifier": "weex", "has_trading_incentive": false}, "last": 0.07478, "volume": 425094.7, "converted_last": {"btc": 7.43321e-07, "eth": 2.28e-05, "usd": 0.074738}, "converted_volume": {"btc": 0.32195617, "eth": 9.877452, "usd": 32371}, "trust_score": "green", "bid_ask_spread_percentage": 0.053519, "timestamp": "2025-11-07T15:03:21+00:00", "last_traded_at": "2025-11-07T15:03:21+00:00", "last_fetch_at": "2025-11-07T15:03:21+00:00", "is_anomaly": false, "is_stale": false, "trade_url": "https://www.weex.com/spot/SQD-USDT", "token_info_url": null, "coin_id": "subsquid", "target_coin_id": "tether", "coin_mcap_usd": 65028498.56333634}, {"base": "SQD", "target": "USDT", "market": {"name": "BingX", "identifier": "bingx", "has_trading_incentive": false}, "last": 0.07397, "volume": 1466326.86, "converted_last": {"btc": 7.35645e-07, "eth": 2.262e-05, "usd": 0.073916}, "converted_volume": {"btc": 1.135887, "eth": 34.928076, "usd": 114131}, "trust_score": "green", "bid_ask_spread_percentage": 0.26907, "timestamp": "2025-11-07T15:08:58+00:00", "last_traded_at": "2025-11-07T15:08:58+00:00", "last_fetch_at": "2025-11-07T15:08:58+00:00", "is_anomaly": false, "is_stale": false, "trade_url": "https://bingx.com/en-us/spot/SQDUSDT", "token_info_url": null, "coin_id": "subsquid", "target_coin_id": "tether", "coin_mcap_usd": 65028498.56333634}, {"base": "SQD", "target": "USDT", "market": {"name": "BitMart", "identifier": "bitmart", "has_trading_incentive": false}, "last": 0.07436, "volume": 8814991.2, "converted_last": {"btc": 7.39514e-07, "eth": 2.276e-05, "usd": 0.074306}, "converted_volume": {"btc": 6.518812, "eth": 200.636, "usd": 655002}, "trust_score": "green", "bid_ask_spread_percentage": 1.729686, "timestamp": "2025-11-07T15:05:17+00:00", "last_traded_at": "2025-11-07T15:05:17+00:00", "last_fetch_at": "2025-11-07T15:08:15+00:00", "is_anomaly": false, "is_stale": false, "trade_url": "https://www.bitmart.com/trade/en?symbol=SQD_USDT", "token_info_url": null, "coin_id": "subsquid", "target_coin_id": "tether", "coin_mcap_usd": 65028498.56333634}, {"base": "0XD4554BEA546EFA83C1E6B389ECAC40EA999B3E78", "target": "0X833589FCD6EDB6E08F4C7C32D4F71B54BDA02913", "market": {"name": "Aerodrome (Base)", "identifier": "aerodrome-base", "has_trading_incentive": false}, "last": 0.07410158833, "volume": 2345431.60039196, "converted_last": {"btc": 7.38937e-07, "eth": 2.274e-05, "usd": 0.074248}, "converted_volume": {"btc": 1.818195, "eth": 55.961, "usd": 182690}, "trust_score": "green", "bid_ask_spread_percentage": 0.603808, "timestamp": "2025-11-07T15:08:39+00:00", "last_traded_at": "2025-11-07T15:08:39+00:00", "last_fetch_at": "2025-11-07T15:08:39+00:00", "is_anomaly": false, "is_stale": false, "trade_url": "https://aerodrome.finance/swap?from=0xd4554bea546efa83c1e6b389ecac40ea999b3e78&to=0x833589fcd6edb6e08f4c7c32d4f71b54bda02913", "token_info_url": null, "coin_id": "subsquid", "target_coin_id": "usd-coin", "coin_mcap_usd": 65028498.56333634}, {"base": "0X1337420DED5ADB9980CFC35F8F2B054EA86F8AB1", "target": "0X82AF49447D8A07E3BD95BD0D56F35241523FBAB1", "market": {"name": "PancakeSwap V3 (Arbitrum)", "identifier": "pancakeswap-v3-arbitrum", "has_trading_incentive": false}, "last": 2.291791771e-05, "volume": 1788953.724016, "converted_last": {"btc": 7.47124e-07, "eth": 2.3e-05, "usd": 0.07507}, "converted_volume": {"btc": 1.368836, "eth": 42.130145, "usd": 137539}, "trust_score": "green", "bid_ask_spread_percentage": 0.603204, "timestamp": "2025-11-07T15:08:30+00:00", "last_traded_at": "2025-11-07T15:08:30+00:00", "last_fetch_at": "2025-11-07T15:08:30+00:00", "is_anomaly": false, "is_stale": false, "trade_url": "https://pancakeswap.finance/swap?inputCurrency=0x1337420ded5adb9980cfc35f8f2b054ea86f8ab1&outputCurrency=0x82af49447d8a07e3bd95bd0d56f35241523fbab1", "token_info_url": null, "coin_id": "subsquid", "target_coin_id": "arbitrum-bridged-weth-arbitrum-one", "coin_mcap_usd": 65028498.56333634}, {"base": "SQD", "target": "USDT", "market": {"name": "MEXC", "identifier": "mxc", "has_trading_incentive": false}, "last": 0.07441, "volume": 1454165.17, "converted_last": {"btc": 7.39013e-07, "eth": 2.269e-05, "usd": 0.07436}, "converted_volume": {"btc": 1.100077, "eth": 33.773909, "usd": 110690}, "trust_score": "green", "bid_ask_spread_percentage": 0.63189, "timestamp": "2025-11-07T15:06:19+00:00", "last_traded_at": "2025-11-07T15:06:19+00:00", "last_fetch_at": "2025-11-07T15:06:19+00:00", "is_anomaly": false, "is_stale": false, "trade_url": "https://www.mexc.com/exchange/SQD_USDT", "token_info_url": null, "coin_id": "subsquid", "target_coin_id": "tether", "coin_mcap_usd": 65028498.56333634}, {"base": "SQD", "target": "EUR", "market": {"name": "LCX Exchange", "identifier": "lcx", "has_trading_incentive": false}, "last": 0.06443, "volume": 631930.47299797, "converted_last": {"btc": 7.41651e-07, "eth": 2.275e-05, "usd": 0.07457}, "converted_volume": {"btc": 0.46867173, "eth": 14.378611, "usd": 47123}, "trust_score": "green", "bid_ask_spread_percentage": 0.294939, "timestamp": "2025-11-07T15:03:35+00:00", "last_traded_at": "2025-11-07T15:03:35+00:00", "last_fetch_at": "2025-11-07T15:03:35+00:00", "is_anomaly": false, "is_stale": false, "trade_url": "https://exchange.lcx.com/trade/SQD_EUR", "token_info_url": null, "coin_id": "subsquid", "coin_mcap_usd": 65028498.56333634}, {"base": "SQD", "target": "USDT", "market": {"name": "Phemex", "identifier": "phemex", "has_trading_incentive": false}, "last": 0.07422, "volume": 947976.9, "converted_last": {"btc": 7.38132e-07, "eth": 2.27e-05, "usd": 0.074166}, "converted_volume": {"btc": 0.69973183, "eth": 21.516472, "usd": 70307}, "trust_score": "green", "bid_ask_spread_percentage": 0.510753, "timestamp": "2025-11-07T15:09:15+00:00", "last_traded_at": "2025-11-07T15:09:15+00:00", "last_fetch_at": "2025-11-07T15:09:15+00:00", "is_anomaly": false, "is_stale": false, "trade_url": "https://phemex.com/spot/trade/SQDUSDT", "token_info_url": null, "coin_id": "subsquid", "target_coin_id": "tether", "coin_mcap_usd": 65028498.56333634}, {"base": "0X4674F73545F1DB4036250FF8C33A39AD1678D864", "target": "0XD4554BEA546EFA83C1E6B389ECAC40EA999B3E78", "market": {"name": "Aerodrome (Base)", "identifier": "aerodrome-base", "has_trading_incentive": false}, "last": 0.03398941712, "volume": 8040419.670344, "converted_last": {"btc": 7.38146e-07, "eth": 2.268e-05, "usd": 0.074247}, "converted_volume": {"btc": 0.16524486, "eth": 5.077949, "usd": 16621.4}, "trust_score": "green", "bid_ask_spread_percentage": 0.610862, "timestamp": "2025-11-07T15:07:34+00:00", "last_traded_at": "2025-11-07T15:07:34+00:00", "last_fetch_at": "2025-11-07T15:07:34+00:00", "is_anomaly": false, "is_stale": false, "trade_url": "https://aerodrome.finance/swap?from=0x4674f73545f1db4036250ff8c33a39ad1678d864&to=0xd4554bea546efa83c1e6b389ecac40ea999b3e78", "token_info_url": null, "coin_id": "degenerate-squid", "target_coin_id": "subsquid", "coin_mcap_usd": 2550856.895921039}, {"base": "SQD", "target": "USDT", "market": {"name": "CoinEx", "identifier": "coinex", "has_trading_incentive": false}, "last": 0.074582, "volume": 148391.19095497, "converted_last": {"btc": 7.40213e-07, "eth": 2.269e-05, "usd": 0.074533}, "converted_volume": {"btc": 0.11411978, "eth": 3.497495, "usd": 11490.87}, "trust_score": "green", "bid_ask_spread_percentage": 0.920417, "timestamp": "2025-11-07T15:00:18+00:00", "last_traded_at": "2025-11-07T15:00:18+00:00", "last_fetch_at": "2025-11-07T15:00:18+00:00", "is_anomaly": false, "is_stale": false, "trade_url": "https://www.coinex.com/en/exchange/sqd-usdt?", "token_info_url": null, "coin_id": "subsquid", "target_coin_id": "tether", "coin_mcap_usd": 65028498.56333634}, {"base": "SQD", "target": "USDT", "market": {"name": "CoinUp.io", "identifier": "coinup", "has_trading_incentive": false}, "last": 0.07422, "volume": 166014.94, "converted_last": {"btc": 7.37132e-07, "eth": 2.262e-05, "usd": 0.07417}, "converted_volume": {"btc": 0.12682801, "eth": 3.892293, "usd": 12761.37}, "trust_score": "yellow", "bid_ask_spread_percentage": 0.147651, "timestamp": "2025-11-07T15:05:18+00:00", "last_traded_at": "2025-11-07T15:05:18+00:00", "last_fetch_at": "2025-11-07T15:05:18+00:00", "is_anomaly": false, "is_stale": false, "trade_url": "https://www.coinup.io/en_US/trade/SQD_USDT", "token_info_url": null, "coin_id": "subsquid", "target_coin_id": "tether", "coin_mcap_usd": 65028498.56333634}, {"base": "SQD", "target": "USDT", "market": {"name": "Bitrue", "identifier": "bitrue", "has_trading_incentive": false}, "last": 0.07437, "volume": 150717.9435, "converted_last": {"btc": 7.38621e-07, "eth": 2.267e-05, "usd": 0.07432}, "converted_volume": {"btc": 0.11132348, "eth": 3.416466, "usd": 11201.32}, "trust_score": "yellow", "bid_ask_spread_percentage": 1.040972, "timestamp": "2025-11-07T15:05:16+00:00", "last_traded_at": "2025-11-07T15:05:16+00:00", "last_fetch_at": "2025-11-07T15:05:16+00:00", "is_anomaly": false, "is_stale": false, "trade_url": "https://www.bitrue.com/trade/sqd_usdt", "token_info_url": null, "coin_id": "subsquid", "target_coin_id": "tether", "coin_mcap_usd": 65028498.56333634}, {"base": "SQD", "target": "USD", "market": {"name": "Crypto.com Exchange", "identifier": "crypto_com", "has_trading_incentive": false}, "last": 0.0751, "volume": 57946.0, "converted_last": {"btc": 7.47975e-07, "eth": 2.297e-05, "usd": 0.0751}, "converted_volume": {"btc": 0.04334214, "eth": 1.331047, "usd": 4351.74}, "trust_score": "red", "bid_ask_spread_percentage": 1.014957, "timestamp": "2025-11-07T12:46:38+00:00", "last_traded_at": "2025-11-07T12:46:38+00:00", "last_fetch_at": "2025-11-07T15:09:41+00:00", "is_anomaly": false, "is_stale": false, "trade_url": "https://crypto.com/exchange/trade/spot/SQD_USD", "token_info_url": null, "coin_id": "subsquid", "coin_mcap_usd": 65028498.56333634}, {"base": "0XD4554BEA546EFA83C1E6B389ECAC40EA999B3E78", "target": "0X833589FCD6EDB6E08F4C7C32D4F71B54BDA02913", "market": {"name": "Aerodrome SlipStream", "identifier": "aerodrome-slipstream", "has_trading_incentive": false}, "last": 0.08518727889, "volume": 42919.6985313185, "converted_last": {"btc": 7.64276e-07, "eth": 2.193e-05, "usd": 0.084376}, "converted_volume": {"btc": 0.03084528, "eth": 0.88491605, "usd": 3405.32}, "trust_score": "green", "bid_ask_spread_percentage": 0.906993, "timestamp": "2025-11-02T14:22:19+00:00", "last_traded_at": "2025-11-02T14:22:19+00:00", "last_fetch_at": "2025-11-02T14:22:19+00:00", "is_anomaly": true, "is_stale": true, "trade_url": "https://aerodrome.finance/swap?from=0xd4554bea546efa83c1e6b389ecac40ea999b3e78&to=0x833589fcd6edb6e08f4c7c32d4f71b54bda02913", "token_info_url": null, "coin_id": "subsquid", "target_coin_id": "usd-coin", "coin_mcap_usd": 65028498.56333634}]}