{
  "ts": "2025-12-05T08:55:46.114585Z",
  "symbol": "B2",
  "token": "0x783c3f003f172c6Ac5AC700218a357d2D66Ee2a2",
  "price_usd": 0.7395,
  "main_pair_hint": "0xc1A780989734a0e5df875cEbe410748562e1c5e6",
  "window_minutes": 40,
  "stats": {
    "total_swaps_scanned": 150,
    "total_swaps_in_window": 150,
    "buys_ge_min_usd": 108,
    "wallet_unici_ge_min_usd": 71,
    "wallet_valutati_topk": 20,
    "wallet_tenuti": 0,
    "wallet_scartati_old": 16,
    "dexscreener_activity_bucket": "h1",
    "dexscreener_bucket_buys": 240,
    "dexscreener_bucket_sells": 263
  },
  "agg": {
    "buyers_total_usd_window_all": 30429.455225214857,
    "buyers_unique_all": 71,
    "top_spenders_all": [
      {
        "address": "0x12c43f031b112fc9a31d4457e3cdaaa67a43441f",
        "sum_buys_usd_window": 3141.0816960160846
      },
      {
        "address": "0xb2ec7ca365d3c2e710da3365dcb6d95fa656e0b5",
        "sum_buys_usd_window": 1744.2033063057374
      },
      {
        "address": "0xcc6e7baccaa963fb85adead8daa7ad65b468e136",
        "sum_buys_usd_window": 1655.1656279365568
      },
      {
        "address": "0x6ed8473772258b2fa3b21b1327ceafca794ce59d",
        "sum_buys_usd_window": 1135.4316579046927
      },
      {
        "address": "0x18f063eac520ca6760bfca45e528dbf658e15a4b",
        "sum_buys_usd_window": 1035.8765503945847
      },
      {
        "address": "0xfcfb018a3f970fac6f3cf0cc55aa7d0afa5cc1ba",
        "sum_buys_usd_window": 936.7675988658801
      },
      {
        "address": "0x90a1fe6cd2de4e1fb467c2fa3be1687c73b92867",
        "sum_buys_usd_window": 928.8308556882487
      },
      {
        "address": "0x346deba242c32165c04686b9860c00dd8ccf7df9",
        "sum_buys_usd_window": 921.4689105537338
      },
      {
        "address": "0xb523c9733ffdbbe2c20a52216e4041973ec2e09f",
        "sum_buys_usd_window": 905.4094576294309
      },
      {
        "address": "0x7a3e3658c471a0eecd5999593af22e7f2ef52367",
        "sum_buys_usd_window": 825.5765469415365
      },
      {
        "address": "0x68c0e8336954bb73011147b1e45f72ebc3702ec0",
        "sum_buys_usd_window": 784.2193887766041
      },
      {
        "address": "0xb22fda69bae708df9f0978e06f5219cca5b95f88",
        "sum_buys_usd_window": 646.9802054736871
      },
      {
        "address": "0xd7c0e1b504563ce64f7e5252e2077440106af713",
        "sum_buys_usd_window": 587.5048827088433
      },
      {
        "address": "0x1839c88134c6a16f94451def2e90ddc1796713dc",
        "sum_buys_usd_window": 584.4649126213341
      },
      {
        "address": "0x124d03193d9f0395f194a517cd7c041c1d99c831",
        "sum_buys_usd_window": 544.0287749726515
      },
      {
        "address": "0xc076ffc269c1f4933f9d10ad4b4c57ab988d85e5",
        "sum_buys_usd_window": 519.7079481481396
      },
      {
        "address": "0x5af44f9f09de227d584400e428fab3bb064b4a5e",
        "sum_buys_usd_window": 514.9439655493813
      },
      {
        "address": "0x6b57c0e92945197048160d31afecc0c5c9ce5ea3",
        "sum_buys_usd_window": 500.966917347554
      },
      {
        "address": "0x878347860dc1f7c32e31e71892616e359f71cf94",
        "sum_buys_usd_window": 478.55861413660483
      },
      {
        "address": "0x8519232f74332eb4ef2bf4f8c6deead8221737c4",
        "sum_buys_usd_window": 475.4188567635431
      }
    ]
  }
}