{
  "ts": "2026-03-15T19:27:36.914260Z",
  "symbol": "RIVER",
  "token": "0xdA7AD9dea9397cffdDAE2F8a052B82f1484252B3",
  "price_usd": 22.92,
  "main_pair_hint": "0x886928EB467EF5E69B4EBc2c8Af4275b21aF41BD",
  "window_minutes": 50,
  "stats": {
    "total_swaps_scanned": 138,
    "total_swaps_in_window": 138,
    "buys_ge_min_usd": 58,
    "wallet_unici_ge_min_usd": 29,
    "total_transfers_scanned": 1116,
    "total_transfers_in_window": 1116,
    "transfers_ge_min_usd": 15,
    "wallet_unici_ge_min_transfers_usd": 12,
    "candidate_wallets_union": 41,
    "eligible_buy_candidates": 1,
    "eligible_transfer_candidates": 0,
    "wallet_valutati_topk": 41,
    "wallet_tenuti": 0,
    "wallet_new_in_results": 0,
    "wallet_scartati_old_buy": 28,
    "wallet_scartati_old_transfer": 12,
    "wallet_scartati_low_balance_usd": 1,
    "wallet_scartati_no_price": 0,
    "budget_exhausted": null,
    "dexscreener_activity_bucket": "h1",
    "dexscreener_bucket_buys": 136,
    "dexscreener_bucket_sells": 304
  },
  "agg": {
    "buyers_total_usd_window_all": 29897.272879280947,
    "buyers_unique_all": 29,
    "transfers_total_usd_window_all": 298911.4702223456,
    "transfers_unique_all": 12,
    "top_spenders_all": [
      {
        "address": "0x5d9b85a8835c871435c6295d3bb4de003e957b3b",
        "sum_buys_usd_window": 6556.107832544435
      },
      {
        "address": "0xb523c9733ffdbbe2c20a52216e4041973ec2e09f",
        "sum_buys_usd_window": 4000.0
      },
      {
        "address": "0xb6d6cc626e9f6743d90585915c263dba23d6e6a0",
        "sum_buys_usd_window": 2942.303930616307
      },
      {
        "address": "0x3e9b19ba0f26ed8ddedb3a5fb310aab0dd790dab",
        "sum_buys_usd_window": 2208.8424225777085
      },
      {
        "address": "0xfa9ad5063222e7f5f4962a66cf4bd56ee5a89619",
        "sum_buys_usd_window": 1982.808553285351
      },
      {
        "address": "0xd10d38534515b45359dd6fbbb4dd092c89eaa910",
        "sum_buys_usd_window": 1982.8076902437629
      },
      {
        "address": "0x0c5bfdfb6ae405f2140c25f1dc079ab25a4c4293",
        "sum_buys_usd_window": 1318.7652164855708
      },
      {
        "address": "0xb9b9fd76f4eda0e3b6a2f0a8102e73bf0e0db84e",
        "sum_buys_usd_window": 1256.3510238947113
      },
      {
        "address": "0xb909fc8062a47152eff099d2f707093298c94c06",
        "sum_buys_usd_window": 1203.0372088646209
      },
      {
        "address": "0x70c39144c734ad6f24f442bbfd11b38c4e030baa",
        "sum_buys_usd_window": 1002.5685814256966
      },
      {
        "address": "0x6d4b076227883705125b03304a1ea720180ea47e",
        "sum_buys_usd_window": 953.9621664406901
      },
      {
        "address": "0x9a13a9fac1644f02890a326d0fbef08302cb89e1",
        "sum_buys_usd_window": 746.1746365759163
      },
      {
        "address": "0xf91e8bf46b9e90909e53c82353c833bb4a5e3a45",
        "sum_buys_usd_window": 554.1521466169376
      },
      {
        "address": "0x5dbdb9a7b29afae35aeb66362a0b6af3de9d0b85",
        "sum_buys_usd_window": 300.4984404365014
      },
      {
        "address": "0x362820adaea13695c0ccedce2de29e2e415f7578",
        "sum_buys_usd_window": 299.94317086760395
      },
      {
        "address": "0xc6107cc9eef41bcc6bb131242786b75a34c9728b",
        "sum_buys_usd_window": 279.2546019386832
      },
      {
        "address": "0x32a91be31870a237397310c1fd16b4b748c41f90",
        "sum_buys_usd_window": 239.9513213061468
      },
      {
        "address": "0x6e3fa341771d857fb9893177cfc56e85a3c53a15",
        "sum_buys_usd_window": 239.93065301589385
      },
      {
        "address": "0x52e868e60b37a637359a010977e4a86b63ab266c",
        "sum_buys_usd_window": 230.35776649861108
      },
      {
        "address": "0xfdbdb9a64a4b4d4f7a12880d69bccfb82952bd33",
        "sum_buys_usd_window": 207.13865536849204
      },
      {
        "address": "0x3dddc72b198743c3f76033dcf06ea83ee265e546",
        "sum_buys_usd_window": 199.6
      },
      {
        "address": "0x2274588fb17c6315210ba8fd117dc1fc4b816ea2",
        "sum_buys_usd_window": 197.144152
      },
      {
        "address": "0xcc3c8267232254fdb2fb05c94b57281d37348741",
        "sum_buys_usd_window": 179.25246015735942
      },
      {
        "address": "0xde69a00e17238361247c308df388d679724bc3b5",
        "sum_buys_usd_window": 158.9113987371739
      },
      {
        "address": "0x6843e9d53af732985e9af951f7f167ecec3a9fb0",
        "sum_buys_usd_window": 150.0
      },
      {
        "address": "0xc1b2aff52877b4a23422f554f3d240be50ec80cf",
        "sum_buys_usd_window": 138.19425485407533
      },
      {
        "address": "0xabba7bef6dffba87d66e6c3d2d612b1a57df2303",
        "sum_buys_usd_window": 135.0
      },
      {
        "address": "0x52589d5dcf8c0650fd9c3967dfd0a4edf9aca3a7",
        "sum_buys_usd_window": 117.229154163752
      },
      {
        "address": "0x64b0b8bae789f2736dff761f0d9b58e50b241e22",
        "sum_buys_usd_window": 116.98544036494489
      }
    ],
    "top_transfers_all": [
      {
        "address": "0xdd3cb5c974601bc3974d908ea4a86020f9999e0c",
        "sum_transfers_usd_window": 203988.00000000003,
        "transfers_count_window": 1,
        "max_transfer_usd_window": 203988.00000000003
      },
      {
        "address": "0x1ab4973a48dc892cd9971ece8e01dcc7688f8f23",
        "sum_transfers_usd_window": 25598.12178,
        "transfers_count_window": 2,
        "max_transfer_usd_window": 16294.893780000002,
        "user_name": "Sadness"
      },
      {
        "address": "0x5950baf9a858e3ea17fd6e753d3ac6f3e9152387",
        "sum_transfers_usd_window": 16294.893780000002,
        "transfers_count_window": 2,
        "max_transfer_usd_window": 8801.19978
      },
      {
        "address": "0x566b30470d7ad97419a48900dc869bd7148736b8",
        "sum_transfers_usd_window": 9303.228000000001,
        "transfers_count_window": 1,
        "max_transfer_usd_window": 9303.228000000001
      },
      {
        "address": "0x886928eb467ef5e69b4ebc2c8af4275b21af41bd",
        "sum_transfers_usd_window": 9194.055439905493,
        "transfers_count_window": 2,
        "max_transfer_usd_window": 5893.575439905493,
        "user_name": "Colle Der Fomento"
      },
      {
        "address": "0xabbeb6e9b9c96a837c99fb9faa908fc7a1df2bc1",
        "sum_transfers_usd_window": 7072.2800185869355,
        "transfers_count_window": 1,
        "max_transfer_usd_window": 7072.2800185869355,
        "user_name": "Howard the Duck"
      },
      {
        "address": "0x4982085c9e2f89f2ecb8131eca71afad896e89cb",
        "sum_transfers_usd_window": 6575.748,
        "transfers_count_window": 1,
        "max_transfer_usd_window": 6575.748,
        "user_name": "Avicii"
      },
      {
        "address": "0x03631c388fb01e0d929627b614eeb501c0ef9dce",
        "sum_transfers_usd_window": 6575.748,
        "transfers_count_window": 1,
        "max_transfer_usd_window": 6575.748
      },
      {
        "address": "0x031942f26a094be40414f442a2f1295e3a5c1680",
        "sum_transfers_usd_window": 3974.767203853121,
        "transfers_count_window": 1,
        "max_transfer_usd_window": 3974.767203853121
      },
      {
        "address": "0xb300000b72deaeb607a12d5f54773d1c19c7028d",
        "sum_transfers_usd_window": 3667.2000000000003,
        "transfers_count_window": 1,
        "max_transfer_usd_window": 3667.2000000000003
      },
      {
        "address": "0xbcb5148b8348b022f8d4fc59d2a7295f6202c7a3",
        "sum_transfers_usd_window": 3366.9480000000003,
        "transfers_count_window": 1,
        "max_transfer_usd_window": 3366.9480000000003
      },
      {
        "address": "0xf45ecc0b00283c607f2f6e93425e4b9f8e7488d8",
        "sum_transfers_usd_window": 3300.4800000000005,
        "transfers_count_window": 1,
        "max_transfer_usd_window": 3300.4800000000005
      }
    ]
  }
}