{
  "ts": "2025-12-03T04:55:01.884395Z",
  "symbol": "BLESS",
  "token": "0x7C8217517ed4711fe2DECCdFefFE8d906b9Ae11F",
  "price_usd": 0.01417,
  "main_pair_hint": "0x49986efbeEdEa3Ab962CA95caF86919860ECc9DB",
  "window_minutes": 40,
  "stats": {
    "total_swaps_scanned": 59,
    "total_swaps_in_window": 59,
    "buys_ge_min_usd": 24,
    "wallet_unici_ge_min_usd": 20,
    "wallet_valutati_topk": 20,
    "wallet_tenuti": 0,
    "wallet_scartati_old": 20,
    "dexscreener_activity_bucket": "h1",
    "dexscreener_bucket_buys": 101,
    "dexscreener_bucket_sells": 66
  },
  "agg": {
    "buyers_total_usd_window_all": 3501.7025712877403,
    "buyers_unique_all": 20,
    "top_spenders_all": [
      {
        "address": "0xb4c0bc67ed1487ca037e48e99e596e8745f68431",
        "sum_buys_usd_window": 393.2234979296946
      },
      {
        "address": "0x3e5523ed87e72347830914d78192cd8e074d3381",
        "sum_buys_usd_window": 381.81903383679867
      },
      {
        "address": "0xd33f4df1d48e2ec2eed06d99fef3d03252a1442a",
        "sum_buys_usd_window": 274.08282061321086
      },
      {
        "address": "0xc1c681a718155776fac9efc50dd66941418e8daf",
        "sum_buys_usd_window": 269.6786064765977
      },
      {
        "address": "0x95dbdd511b74d815b01408b6f8684ca7ff5295b6",
        "sum_buys_usd_window": 254.48764944854253
      },
      {
        "address": "0xf9cd6dc301d648327ee7774a0f0f973275ffbffc",
        "sum_buys_usd_window": 177.23378603844637
      },
      {
        "address": "0xc57bdfaf7dc2317c335fe4b9b2eb22308b861605",
        "sum_buys_usd_window": 149.91024778885617
      },
      {
        "address": "0x71fb19f8f578a13dd8be299f155d7ae643089c48",
        "sum_buys_usd_window": 149.48918215675369
      },
      {
        "address": "0xb80b21025f8e166783c1e2aec8a1d3df62370b4f",
        "sum_buys_usd_window": 142.72506249591095
      },
      {
        "address": "0xd47ee24477d6a7449d907481389c7afa52782c5f",
        "sum_buys_usd_window": 136.90876942102716
      },
      {
        "address": "0x1e3346a932da33048db8621faa6760f89d839f5b",
        "sum_buys_usd_window": 136.79338930980185
      },
      {
        "address": "0xc184b52987063cfbc02f3dabcac3b5b7c727a201",
        "sum_buys_usd_window": 127.64843210788591
      },
      {
        "address": "0x3ad64217dad55547385213e57b5eee62d572db2b",
        "sum_buys_usd_window": 122.88872972954158
      },
      {
        "address": "0xb627481e3cc706ea32f982b809223a6d33160533",
        "sum_buys_usd_window": 119.67350398589551
      },
      {
        "address": "0x7f9e8f2320c5f1c48702c9a4fd28ef02b9a22e8e",
        "sum_buys_usd_window": 119.5819460013958
      },
      {
        "address": "0x19556d3e35c3415cc206312feb66773bfa3ac90c",
        "sum_buys_usd_window": 115.80078173451386
      },
      {
        "address": "0x9b103675b854c9b52be6feae129d88e30bd8258d",
        "sum_buys_usd_window": 115.80075069322969
      },
      {
        "address": "0xf0caa69a08f737f781f661898719e01c243ea95b",
        "sum_buys_usd_window": 108.3868998378392
      },
      {
        "address": "0x59ff3991b2af191c2086cb984a7041349b77b303",
        "sum_buys_usd_window": 105.54755842822809
      },
      {
        "address": "0xce0aad25a0651bbe5d1388e8cc7ed84c531bb351",
        "sum_buys_usd_window": 100.02192325357015
      }
    ]
  }
}