{
  "ts": "2025-11-19T15:48:26.839591Z",
  "symbol": "KGEN",
  "token": "0xF3d5b4c34Ed623478cc5141861776E6cf7AE3A1E",
  "price_usd": 0.2109,
  "main_pair_hint": "0x81965714e2A1EC25fB8BcB3DE60a11FE6bCA929a",
  "window_minutes": 40,
  "stats": {
    "total_swaps_scanned": 129,
    "total_swaps_in_window": 129,
    "buys_ge_min_usd": 3,
    "wallet_unici_ge_min_usd": 3,
    "wallet_valutati_topk": 3,
    "wallet_tenuti": 0,
    "wallet_scartati_old": 3,
    "dexscreener_activity_bucket": "h1",
    "dexscreener_bucket_buys": 35,
    "dexscreener_bucket_sells": 49
  },
  "agg": {
    "buyers_total_usd_window_all": 407.8145647884425,
    "buyers_unique_all": 3,
    "top_spenders_all": [
      {
        "address": "0x9999b0cdd35d7f3b281ba02efc0d228486940515",
        "sum_buys_usd_window": 207.8145647884425
      },
      {
        "address": "0xe4945f8672bd4f1547a3bdf8b1181e1609de404f",
        "sum_buys_usd_window": 100.0
      },
      {
        "address": "0xab8cc4d72cea6b3036421eeb2a3585e60ebad1e9",
        "sum_buys_usd_window": 100.0
      }
    ]
  }
}